Workbook

Sheet Login
A1: Project Name | B1: UMPay
A2: Module/Feature Name | B2: Login | P2: HIGH | Q2: MEDIUM | R2: LOW
A3: Reference Document | N3: PASS | O3: =COUNTIF(K:K,"PASS") | P3: =COUNTIFS(K:K,"PASS",L:L,"HIGH") | Q3: =COUNTIFS(K:K,"PASS",L:L,"MEDIUM") | R3: =COUNTIFS(K:K,"PASS",L:L,"LOW")
A4: Created By | B4: KIMA | N4: FAIL | O4: =COUNTIF(K:K,"FAIL") | P4: =COUNTIFS(K:K,"FAIL",L:L,"HIGH") | Q4: =COUNTIFS(K:K,"FAIL",L:L,"MEDIUM") | R4: =COUNTIFS(K:K,"FAIL",L:L,"LOW")
A5: Date of Creation | B5: 46170 | N5: PENDING | O5: =COUNTIF(K:K,"PENDING") | P5: =COUNTIFS(K:K,"PENDING",L:L,"HIGH") | Q5: =COUNTIFS(K:K,"PENDING",L:L,"MEDIUM") | R5: =COUNTIFS(K:K,"PENDING",L:L,"LOW")
A6: Date of Review | B6: 46136
A8: TEST CASE ID | B8: TEST SCENARIO | C8: TEST CASE | D8: TEST CATEGORY | E8: PRE-CONDITION | F8: TEST STEPS | G8: TEST DATA | H8: EXPECTED RESULTS | I8: POST CONDITION | J8: ACTUAL RESULT | K8: STATUS | L8: PRIORITY | M8: TESTER | N8: TEST DATE | O8: DEVICE | P8: BROWSER | Q8: ISSUE LINK | R8: COMMENT | S8: Run
A9: TC_001 | B9: Login Using Email | C9: Successful Login and Logout using email | D9: Positive | E9: User is on Login page. | F9: -Given I log into the UMPay application with valid email credentials using "<row>" of "<excelSheetName>" of "<excelFileName>" -When I check and validate all the homepage contents -Then I should be able to successfully log out | G9: Valid UMPay email credentials | H9: User should be able to login and logout | I9: User is on login page | J9: User can login and logout | K9: PASS | L9: HIGH | N9: 46104 | O9: Window OS | P9: Edge | S9: Run
A10: TC_002 | B10: Login Using Phone | C10: Successful Login and Logout using phone | D10: Positive | E10: User is on Login page. | F10: -I sign in with the phone number in "<row>" of "<excelSheetName>" of "<excelFileName>" -When I check and validate all the homepage contents -Then I should be able to successfully log out | G10: Valid UMPay phone credentials | H10: User should be able to login and logout | I10: User is on login page | J10: User can login and logout | K10: PASS | L10: HIGH | N10: 46104 | O10: Window OS | P10: Edge | S10: Run
A11: TC_003 | B11: Login Using Email | C11: An email address that is not a valid address is rejected before anything is sent | D11: Negative | E11: User is on Login page. | F11: -I am on the UMPay login page -When I try to sign in with the email address in "<row>" of "<excelSheetName>" of "<excelFileName>" -Then the browser should reject the login "email" field with the message in "<row>" of "<excelSheetName>" of "<excelFileName>" -And I should still be on the login page | G11: Invalid email address | H11: User should not be able to login | I11: User is on login page | J11: User can not login | K11: PASS | L11: HIGH | N11: 46104 | O11: Window OS | P11: Edge | S11: Run
A12: TC_004 | B12: Login Using Email | C12: An empty email address cannot be submitted | D12: Negative | E12: User is on Login page. | F12: -I am on the UMPay login page -When I try to sign in with the email address in "<row>" of "<excelSheetName>" of "<excelFileName>" -Then the browser should reject the login "email" field with the message in "<row>" of "<excelSheetName>" of "<excelFileName>" -And I should still be on the login page | G12: Invalid email address | H12: User should not be able to login | I12: User is on login page | J12: User can not login | K12: PASS | L12: HIGH | N12: 46104 | O12: Window OS | P12: Edge | S12: Run
A13: TC_005 | B13: Login Using Email | C13: An email address nobody holds is turned away by the server | D13: Negative | E13: User is on Login page. | F13: -I am on the UMPay login page -When I try to sign in with the email address in "<row>" of "<excelSheetName>" of "<excelFileName>" -Then the sign in should be refused with the message in "<row>" of "<excelSheetName>" of "<excelFileName>" -And I should still be on the login page | G13: Invalid email address | H13: User should not be able to login | I13: User is on login page | J13: User can not login | K13: PASS | L13: HIGH | N13: 46104 | O13: Window OS | P13: Edge | S13: Run
A14: TC_006 | B14: Login Using Email | C14: A password under six characters is refused | D14: Negative | E14: User is on Login page. | F14: -I am on the UMPay login page -When I try to sign in with the email address in "<row>" of "<excelSheetName>" of "<excelFileName>" -Then the form should complain with the message in "<row>" of "<excelSheetName>" of "<excelFileName>" -And I should still be on the login page | G14: Invalid email address | H14: User should not be able to login | I14: User is on login page | J14: User can not login | K14: PASS | L14: HIGH | N14: 46104 | O14: Window OS | P14: Edge | S14: Run
A15: TC_007 | B15: Login Using Email | C15: An empty password cannot be submitted | D15: Negative | E15: User is on Login page. | F15: -I am on the UMPay login page -When I try to sign in with the email address in "<row>" of "<excelSheetName>" of "<excelFileName>" -Then the browser should reject the login "password" field with the message in "<row>" of "<excelSheetName>" of "<excelFileName>" -And I should still be on the login page | G15: Invalid email address | H15: User should not be able to login | I15: User is on login page | J15: User can not login | K15: PASS | L15: HIGH | N15: 46104 | O15: Window OS | P15: Edge | S15: Run
A16: TC_008 | B16: Login Using Phone | C16: A phone number that is not a number is rejected before anything is sent | D16: Negative | E16: User is on Login page. | F16: -I am on the UMPay login page -When I try to sign in with the phone number in "<row>" of "<excelSheetName>" of "<excelFileName>" -Then the browser should reject the login "phone" field with the message in "<row>" of "<excelSheetName>" of "<excelFileName>" -And I should still be on the login page | G16: Invalid phone number | H16: User should not be able to login | I16: User is on login page | J16: User can not login | K16: PASS | L16: HIGH | N16: 46104 | O16: Window OS | P16: Edge | S16: Run
A17: TC_009 | B17: Login Using Phone | C17: An empty phone number cannot be submitted | D17: Negative | E17: User is on Login page. | F17: -I am on the UMPay login page -When I try to sign in with the phone number in "<row>" of "<excelSheetName>" of "<excelFileName>" -Then the browser should reject the login "phone" field with the message in "<row>" of "<excelSheetName>" of "<excelFileName>" -And I should still be on the login page | G17: Invalid phone number | H17: User should not be able to login | I17: User is on login page | J17: User can not login | K17: PASS | L17: HIGH | N17: 46104 | O17: Window OS | P17: Edge | S17: Run
A18: TC_010 | B18: Login Using Phone | C18: A phone number shorter than six digits is refused | D18: Negative | E18: User is on Login page. | F18: -I am on the UMPay login page -When I try to sign in with the phone number in "<row>" of "<excelSheetName>" of "<excelFileName>" -Then the sign in should be refused with the message in "<row>" of "<excelSheetName>" of "<excelFileName>" -And I should still be on the login page | G18: Invalid phone number | H18: User should not be able to login | I18: User is on login page | J18: User can not login | K18: PASS | L18: HIGH | N18: 46104 | O18: Window OS | P18: Edge | S18: Run
A19: TC_011 | B19: Login Using Phone | C19: A phone number nobody holds is turned away by the server | D19: Negative | E19: User is on Login page. | F19: -I am on the UMPay login page -When I try to sign in with the phone number in "<row>" of "<excelSheetName>" of "<excelFileName>" -Then the sign in should be refused with the message in "<row>" of "<excelSheetName>" of "<excelFileName>" -And I should still be on the login page | G19: Invalid phone number | H19: User should not be able to login | I19: User is on login page | J19: User can not login | K19: PASS | L19: HIGH | N19: 46104 | O19: Window OS | P19: Edge | S19: Run
A20: TC_012 | B20: Login Using Phone | C20: The phone box keeps a leading zero | D20: Negative | E20: User is on Login page. | F20: -I am on the UMPay login page -When I enter the phone number in "<row>" of "<excelSheetName>" of "<excelFileName>" without signing in -Then the phone number should be kept as typed in "<row>" of "<excelSheetName>" of "<excelFileName>" | G20: Invalid phone number | H20: User should not be able to login | I20: User is on login page | J20: User can not login | K20: PASS | L20: HIGH | N20: 46104 | O20: Window OS | P20: Edge | S20: Run
... A23: TC_015 | B23: Login Using Phone | C23: Three wrong passwords in a row lock the account | D23: Negative | E23: User is on Login page. | F23: -I am on the UMPay login page -When I try to sign in with the email address in "<row>" of "<excelSheetName>" of "<excelFileName>" -And I try to sign in with the email address in "<row>" of "<excelSheetName>" of "<excelFileName>" -And I try to sign in with the email address in "<row>" of "<excelSheetName>" of "<excelFileName>" | G23: Valid UMPay | H23: User should not be able to login | I23: User is on login page | J23: User can not login | K23: PASS | L23: HIGH | N23: 46104 | O23: Window OS | P23: Edge | S23: Run
A24: TC_016 | B24: Login | C24: Forgot password reaches the reset page | D24: Positive | E24: User is on the login page | F24: -Given I am on the UMPay "<page>" page -When I follow the Forgot password link -Then the password reset page should open | G24: No account needed | H24: The Forgot password link should open the password reset page, since somebody locked out of their account has to be able to reach it without signing in | I24: User is on the password reset page | J24: The Forgot password link opened the password reset page | K24: PASS | L24: HIGH | M24: KIMA | N24: 46273 | O24: Window OS | P24: Chromium | S24: Run
A25: TC_017 | B25: Login | C25: A new user can reach registration from the login page | D25: Positive | E25: User is on the login page | F25: -Given I am on the UMPay "<page>" page -When I follow the Register link -Then the registration page should open | G25: No account needed | H25: The Register link should open the registration page, so somebody without an account can get one from where they landed | I25: User is on the registration page | J25: The Register link opened the registration page | K25: PASS | L25: MEDIUM | M25: KIMA | N25: 46273 | O25: Window OS | P25: Chromium | S25: Run
A26: TC_018 | B26: Login | C26: Customer Service can be reached without signing in | D26: Positive | E26: User is on the login page | F26: -Given I am on the UMPay "<page>" page -When I open Customer Service from the login page -Then the customer service chat should open | G26: No account needed | H26: The support bubble should open the chat without signing in, since somebody who cannot sign in is exactly who needs to reach support | I26: The customer service chat is open | J26: Pressing the support bubble opened the customer service chat, which is served as a separate application in an iframe. Worth noting about the page itself: two buttons are pinned to that corner, and the second declares z-index 9999 yet is drawn underneath the first, whose image overlaps it - so anything addressing that second button is intercepted every time | K26: PASS | L26: HIGH | M26: KIMA | N26: 46273 | O26: Window OS | P26: Chromium | S26: Run

Sheet Register
A1: Project Name | B1: UMPay
A2: Module/Feature Name | B2: Register | P2: HIGH | Q2: MEDIUM | R2: LOW
A3: Reference Document | N3: PASS | O3: =COUNTIF(K:K,"PASS") | P3: =COUNTIFS(K:K,"PASS",L:L,"HIGH") | Q3: =COUNTIFS(K:K,"PASS",L:L,"MEDIUM") | R3: =COUNTIFS(K:K,"PASS",L:L,"LOW")
A4: Created By | B4: KIMA | N4: FAIL | O4: =COUNTIF(K:K,"FAIL") | P4: =COUNTIFS(K:K,"FAIL",L:L,"HIGH") | Q4: =COUNTIFS(K:K,"FAIL",L:L,"MEDIUM") | R4: =COUNTIFS(K:K,"FAIL",L:L,"LOW")
A5: Date of Creation | B5: 46170 | N5: PENDING | O5: =COUNTIF(K:K,"PENDING") | P5: =COUNTIFS(K:K,"PENDING",L:L,"HIGH") | Q5: =COUNTIFS(K:K,"PENDING",L:L,"MEDIUM") | R5: =COUNTIFS(K:K,"PENDING",L:L,"LOW")
A6: Date of Review | B6: 46170
A8: TEST CASE ID | B8: TEST SCENARIO | C8: TEST CASE | D8: TEST CATEGORY | E8: PRE-CONDITION | F8: TEST STEPS | G8: TEST DATA | H8: EXPECTED RESULTS | I8: POST CONDITION | J8: ACTUAL RESULT | K8: STATUS | L8: PRIORITY | M8: TESTER | N8: TEST DATE | O8: DEVICE | P8: BROWSER | Q8: ISSUE LINK | R8: COMMENT | S8: Run
A9: TC_001 | B9: Registration | C9: Successful registration with a new email address | D9: Positive | E9: User is on Register Page. | F9: -When I register with an email address using "<row>" of "<excelSheetName>" of "<excelFileName>" -And I enter the verification code sent to the email address -Then the registration should be accepted -When I accept the policies shown to a new account -And I set a PIN security code -And I skip the two factor authentication prompt -Then I should land on the UMPay home page -And I should see the account wallets on the home page | G9: Valid email address | H9: User should be able to register successfully | I9: User is registered | J9: User can register successfully | K9: PASS | L9: HIGH | M9: KIMA | O9: Window OS | P9: Edge | S9: Run
A10: TC_002 | B10: Registration | C10: Successful registration with a phone number | D10: Positive | E10: User is on Register Page. | F10: -When I register with a phone number using "<row>" of "<excelSheetName>" of "<excelFileName>" -Then the registration should reach the phone verification step | G10: Valid phone number | H10: User should be able to register successfully | I10: User is registered | J10: User can register successfully | K10: PASS | L10: HIGH | M10: KIMA | O10: Window OS | P10: Edge | S10: Run
A11: TC_003 | B11: Registration | C11: Registration is rejected for an email address that is already in use | D11: Negative | E11: User is on Register Page. | F11: -When I register with an email address using "<row>" of "<excelSheetName>" of "<excelFileName>" -Then the registration should be rejected with the message in "<row>" of "<excelSheetName>" of "<excelFileName>" | G11: Email already used | H11: User should not be able to register | I11: User is not registered | J11: User can not register | K11: PASS | L11: HIGH | M11: KIMA | O11: Window OS | P11: Edge | S11: Run
A12: TC_004 | B12: Registration | C12: Registration is rejected for phone number that is already in use | D12: Negative | E12: User is on Register Page. | F12: -When I register with a phone number using "<row>" of "<excelSheetName>" of "<excelFileName>" -Then the registration should be rejected with the message in "<row>" of "<excelSheetName>" of "<excelFileName>" | G12: Phone number already used | H12: User should not be able to register | I12: User is not registered | J12: User can not register | K12: PASS | L12: HIGH | M12: KIMA | O12: Window OS | P12: Edge | S12: Run
A13: TC_005 | B13: Registration | C13: Registration is rejected when the captcha code is wrong | D13: Negative | E13: User is on Register Page. | F13: -When I register with an email address using "<row>" of "<excelSheetName>" of "<excelFileName>" -Then the registration should be rejected with the message in "<row>" of "<excelSheetName>" of "<excelFileName>" | G13: Any valid email or phone number | H13: User should not be able to register | I13: User is not registered | J13: User can not register | K13: PASS | L13: HIGH | M13: KIMA | O13: Window OS | P13: Edge | S13: Run
A14: TC_006 | B14: Registration | C14: Registration is blocked when the password is shorter than six characters | D14: Negative | E14: User is on Register Page. | F14: -When I fill the registration form using "<row>" of "<excelSheetName>" of "<excelFileName>" without submitting it -Then the browser should reject the "password" field with the message "Must be at least 6 characters alphanumeric!" | G14: Any valid email or phone number | H14: User should not be able to register | I14: User is not registered | J14: User can not register | K14: PASS | L14: HIGH | M14: KIMA | O14: Window OS | P14: Edge | S14: Run
A15: TC_007 | B15: Register | C15: Existing users can navigate to the login page from the registration page | D15: Positive | E15: User is on the registration page | F15: -Given I am on the UMPay "<page>" page -Then I should be able to go to the login page from the registration page | G15: No account needed | H15: The registration page should offer a way back to the login page for somebody who already has an account | I15: User is on the login page | J15: The link on the registration page opened the login page | K15: PASS | L15: MEDIUM | M15: KIMA | N15: 46273 | O15: Window OS | P15: Chromium | S15: Run

Sheet Reset_Password
A1: Project Name | B1: UMPay
A2: Module/Feature Name | B2: Reset Password | P2: HIGH | Q2: MEDIUM | R2: LOW
A3: Reference Document | N3: PASS | O3: =COUNTIF(K:K,"PASS") | P3: =COUNTIFS(K:K,"PASS",L:L,"HIGH") | Q3: =COUNTIFS(K:K,"PASS",L:L,"MEDIUM") | R3: =COUNTIFS(K:K,"PASS",L:L,"LOW")
A4: Created By | B4: KIMA | N4: FAIL | O4: =COUNTIF(K:K,"FAIL") | P4: =COUNTIFS(K:K,"FAIL",L:L,"HIGH") | Q4: =COUNTIFS(K:K,"FAIL",L:L,"MEDIUM") | R4: =COUNTIFS(K:K,"FAIL",L:L,"LOW")
A5: Date of Creation | B5: 46170 | N5: PENDING | O5: =COUNTIF(K:K,"PENDING") | P5: =COUNTIFS(K:K,"PENDING",L:L,"HIGH") | Q5: =COUNTIFS(K:K,"PENDING",L:L,"MEDIUM") | R5: =COUNTIFS(K:K,"PENDING",L:L,"LOW")
A6: Date of Review | B6: 46136
A8: TEST CASE ID | B8: TEST SCENARIO | C8: TEST CASE | D8: TEST CATEGORY | E8: PRE-CONDITION | F8: TEST STEPS | G8: TEST DATA | H8: EXPECTED RESULTS | I8: POST CONDITION | J8: ACTUAL RESULT | K8: STATUS | L8: PRIORITY | M8: TESTER | N8: TEST DATE | O8: DEVICE | P8: BROWSER | Q8: ISSUE LINK | R8: COMMENT | S8: Run
A9: TC_001 | B9: Reset Password | C9: The reset form refuses a phone number that is not a number | D9: Positive | E9: -User is on Reset Password Page | F9: -I am on the UMPay password reset page -When I fill the phone reset form from "<row>" of "<excelSheetName>" of "<excelFileName>" without sending it -And I send the reset form -Then the reset form should complain with the message in "<row>" of "<excelSheetName>" of "<excelFileName>" -And the reset form should still be shown | G9: Invalid Phone Number | H9: User should not be able to reset | I9: User is still on Reset Password Page. | J9: User can not reset | K9: PASS | L9: HIGH | M9: KIMA | N9: 46104 | O9: Window OS | P9: Edge | S9: Run
A10: TC_002 | B10: Reset Password | C10: The reset form cannot be sent without a phone number | D10: Positive | E10: -User is on Reset Password Page | F10: -I am on the UMPay password reset page When I fill the phone reset form from "<row>" of "<excelSheetName>" of "<excelFileName>" without sending it And I send the reset form Then the browser should reject the reset "phone" field with the message in "<row>" of "<excelSheetName>" of "<excelFileName>" And the reset form should still be shown | G10: Invalid Phone Number | H10: User should not be able to reset | I10: User is still on Reset Password Page. | J10: User can not reset | K10: PASS | L10: HIGH | M10: KIMA | N10: 46104 | O10: Window OS | P10: Edge | S10: Run
A11: TC_003 | B11: Reset Password | C11: The reset phone box keeps a leading zero | D11: Positive | E11: -User is on Reset Password Page | F11: -I am on the UMPay password reset page -When I fill the phone reset form from "<row>" of "<excelSheetName>" of "<excelFileName>" without sending it -Then the reset phone number should be kept as typed in "<row>" of "<excelSheetName>" of "<excelFileName>" | G11: Valid UNCS Admin credentials. | H11: User should not be able to reset | I11: User is still on Reset Password Page. | J11: User can not reset | K11: PASS | L11: HIGH | M11: KIMA | N11: 46104 | O11: Window OS | P11: Edge | S11: Run
A12: TC_004 | B12: Reset Password | C12: The reset form cannot be sent without a captcha | D12: Positive | E12: -User is on Reset Password Page | F12: -I am on the UMPay password reset page -When I fill the phone reset form from "<row>" of "<excelSheetName>" of "<excelFileName>" without sending it -And I send the reset form -Then the browser should reject the reset "captcha" field with the message in "<row>" of "<excelSheetName>" of "<excelFileName>" -And the reset form should still be shown | G12: Valid UNCS Admin credentials. | H12: User should not be able to reset | I12: User is still on Reset Password Page. | J12: User can not reset | K12: PASS | L12: HIGH | M12: KIMA | N12: 46104 | O12: Window OS | P12: Edge | S12: Run
A13: TC_005 | B13: Reset Password | C13: The email reset form cannot be sent without a captcha either | D13: Positive | E13: -User is on Reset Password Page | F13: -I am on the UMPay password reset page -When I fill the email reset form from "<row>" of "<excelSheetName>" of "<excelFileName>" without sending it -And I send the reset form -Then the browser should reject the reset "captcha" field with the message in "<row>" of "<excelSheetName>" of "<excelFileName>" -And the reset form should still be shown | G13: Valid UNCS Admin credentials. | H13: User should not be able to reset | I13: User is still on Reset Password Page. | J13: User can not reset | K13: PASS | L13: HIGH | M13: KIMA | N13: 46104 | O13: Window OS | P13: Edge | S13: Run
A14: TC_006 | B14: Reset Password | C14: The reset form refuses an email address that is not a valid address | D14: Positive | E14: -User is on Reset Password Page | F14: -I am on the UMPay password reset page -When I fill the email reset form from "<row>" of "<excelSheetName>" of "<excelFileName>" without sending it -And I send the reset form -Then the browser should reject the reset "email" field with the message in "<row>" of "<excelSheetName>" of "<excelFileName>" -And the reset form should still be shown | G14: Valid UNCS Admin credentials. | H14: User should not be able to reset | I14: User is still on Reset Password Page. | J14: User can not reset | K14: PASS | L14: HIGH | M14: KIMA | N14: 46104 | O14: Window OS | P14: Edge | S14: Run
A15: TC_007 | B15: Reset Password | C15: A new captcha can be asked for on the phone reset form | D15: Positive | E15: -User is on Reset Password Page | F15: -I am on the UMPay password reset page -When I ask the reset form for a new captcha -Then a different captcha image should be shown | G15: Valid UNCS Admin credentials. | H15: User should not be able to reset | I15: User is still on Reset Password Page. | J15: User can not reset | K15: PASS | L15: HIGH | M15: KIMA | N15: 46104 | O15: Window OS | P15: Edge | S15: Run
A16: TC_008 | B16: Reset Password | C16: A new captcha can be asked for on the email reset form | D16: Positive | E16: -User is on Reset Password Page | F16: -I am on the UMPay password reset page -When I fill the email reset form from "<row>" of "<excelSheetName>" of "<excelFileName>" without sending it -And I ask the reset form for a new captcha -Then a different captcha image should be shown | G16: Valid UNCS Admin credentials. | H16: User should not be able to reset | I16: User is still on Reset Password Page. | J16: User can not reset | K16: PASS | L16: HIGH | M16: KIMA | N16: 46104 | O16: Window OS | P16: Edge | S16: Run
A17: TC_009 | B17: Reset Password | C17: A wrong captcha is refused on the phone reset form | D17: Negative | E17: -User is on Reset Password Page | F17: -I am on the UMPay password reset page -When I ask to reset the password by phone using "<row>" of "<excelSheetName>" of "<excelFileName>" -Then the reset should be refused with the message in "<row>" of "<excelSheetName>" of "<excelFileName>" -And the reset form should still be shown | G17: Valid UNCS Admin credentials. | H17: User should not be able to reset | I17: User is still on Reset Password Page. | J17: User can not reset | K17: PASS | L17: HIGH | M17: KIMA | N17: 46104 | O17: Window OS | P17: Edge | S17: Run
A18: TC_010 | B18: Reset Password | C18: A wrong captcha is refused on the email reset form | D18: Negative | E18: -User is on Reset Password Page | F18: -I am on the UMPay password reset page -When I ask to reset the password by email using "<row>" of "<excelSheetName>" of "<excelFileName>" -Then the reset should be refused with the message in "<row>" of "<excelSheetName>" of "<excelFileName>" -And the reset form should still be shown | G18: Valid UNCS Admin credentials. | H18: User should not be able to reset | I18: User is still on Reset Password Page. | J18: User can not reset | K18: PASS | L18: HIGH | M18: KIMA | N18: 46104 | O18: Window OS | P18: Edge | S18: Run
A19: TC_011 | B19: Reset Password | C19: A phone number shorter than six digits gets no reset | D19: Negative | E19: -User is on Reset Password Page | F19: -I am on the UMPay password reset page -When I ask to reset the password by phone using "<row>" of "<excelSheetName>" of "<excelFileName>" -Then the reset should be refused with the message in "<row>" of "<excelSheetName>" of "<excelFileName>" -And the reset form should still be shown | G19: Valid UNCS Admin credentials. | H19: User should not be able to reset | I19: User is still on Reset Password Page. | J19: User can not reset | K19: PASS | L19: HIGH | M19: KIMA | N19: 46104 | O19: Window OS | P19: Edge | S19: Run
A20: TC_012 | B20: Reset Password | C20: A phone number nobody holds learns nothing about itself | D20: Negative | E20: -User is on Reset Password Page | F20: -I am on the UMPay password reset page -When I ask to reset the password by phone using "<row>" of "<excelSheetName>" of "<excelFileName>" -Then the verification step should be reached | G20: Valid UNCS Admin credentials. | H20: User should not be able to reset | I20: User is still on Reset Password Page. | J20: User can not reset | K20: PASS | L20: HIGH | M20: KIMA | N20: 46104 | O20: Window OS | P20: Edge | S20: Run
... A24: TC_016 | B24: Reset Password | C24: Going back from the verification step should return to the form | D24: Negative | E24: User is on the password reset page | F24: -Given I am on the UMPay password reset page -When I ask to reset the password by email using "<row>" of "<excelSheetName>" of "<excelFileName>" -Then the verification step should be reached -When I go back from the verification step -Then the reset form should be shown again | G24: Email: the registered address | H24: Going back from the verification step should return to the reset form rather than stranding somebody who mistyped their address | I24: User is on the reset form | J24: COULD NOT BE RUN - the platform answered the one-time-code request with 400 "Too Many Requests" (POST /api/notification/otp), so the verification step was never reached and going back from it could not be tried. This says nothing about the application either way; the account has simply asked for too many codes today. To be re-run once the limit clears | K24: PENDING | L24: MEDIUM | M24: KIMA | N24: 46273 | O24: Window OS | P24: Chromium | S24: Run

Sheet Deposit
A1: Project Name | B1: UMPay
A2: Module/Feature Name | B2: Deposit | P2: HIGH | Q2: MEDIUM | R2: LOW
A3: Reference Document | N3: PASS | O3: =COUNTIF(K:K,"PASS") | P3: =COUNTIFS(K:K,"PASS",L:L,"HIGH") | Q3: =COUNTIFS(K:K,"PASS",L:L,"MEDIUM") | R3: =COUNTIFS(K:K,"PASS",L:L,"LOW")
A4: Created By | B4: KIMA | N4: FAIL | O4: =COUNTIF(K:K,"FAIL") | P4: =COUNTIFS(K:K,"FAIL",L:L,"HIGH") | Q4: =COUNTIFS(K:K,"FAIL",L:L,"MEDIUM") | R4: =COUNTIFS(K:K,"FAIL",L:L,"LOW")
A5: Date of Creation | B5: 46170 | N5: PENDING | O5: =COUNTIF(K:K,"PENDING") | P5: =COUNTIFS(K:K,"PENDING",L:L,"HIGH") | Q5: =COUNTIFS(K:K,"PENDING",L:L,"MEDIUM") | R5: =COUNTIFS(K:K,"PENDING",L:L,"LOW")
A6: Date of Review | B6: 46170
A8: TEST CASE ID | B8: TEST SCENARIO | C8: TEST CASE | D8: TEST CATEGORY | E8: PRE-CONDITION | F8: TEST STEPS | G8: TEST DATA | H8: EXPECTED RESULTS | I8: POST CONDITION | J8: ACTUAL RESULT | K8: STATUS | L8: PRIORITY | M8: TESTER | N8: TEST DATE | O8: DEVICE | P8: BROWSER | Q8: ISSUE LINK | R8: COMMENT | S8: Run
A9: TC_001 | B9: Deposit | C9: Successful Deposit Transaction | D9: Positive | E9: User is on Deposit page | F9: -Given I log into the UMPay application with valid email credentials using "<row>" of "<excelSheetName>" of "<excelFileName>" -When I navigate to Deposit page -Then I should be able to initiate a deposit transaction using "<row>" of "<excelSheetName>" of "<excelFileName>" | G9: Valid UMPay credentials | H9: User should be able to perform deposit successfully | I9: User is navigated back to home screen | J9: User can perform deposit successfully | K9: PASS | L9: HIGH | M9: KIMA | O9: Window OS | P9: Edge | S9: Run
A10: TC_002 | B10: Deposit | C10: The deposit form offers a wallet for every currency the account holds | D10: Positive | E10: User is on Deposit page | F10: -I log into the UMPay application with valid email credentials using "1" of "sheet1" of "Deposit_TestData.xlsx" -When I navigate to Deposit page -Then the deposit currency list should offer "BDT, BRL, HKD, IDR, MXN, MYR, PHP, THB, USD, VND" | G10: Valid UMPay credentials | H10: User should be able to see all the currency wallet | I10: User is still on Deposit page | J10: User can see all the currency wallet | K10: PASS | L10: HIGH | M10: KIMA | O10: Window OS | P10: Edge | S10: Run
A11: TC_003 | B11: Deposit | C11: An amount below the minimum is refused | D11: Negative | E11: User is on Deposit page | F11: -Given I log into the UMPay application with valid email credentials using "1" of "sheet1" of "Deposit_TestData.xlsx" -When I navigate to Deposit page -And I choose the "HKD" wallet on the Deposit page -And I enter "50" as the deposit amount -Then the deposit amount should be refused with "Please input an amount of limit min or above!" | G11: Valid UMPay credentials | H11: User should not be able to deposit amount lower than limit | I11: User is still on Deposit page | J11: User can not deposit amount lower than limit | K11: PASS | L11: HIGH | M11: KIMA | O11: Window OS | P11: Edge | S11: Run
A12: TC_004 | B12: Deposit | C12: An amount above the maximum is refused | D12: Negative | E12: User is on Deposit page | F12: -I log into the UMPay application with valid email credentials using "1" of "sheet1" of "Deposit_TestData.xlsx" -When I navigate to Deposit page -And I choose the "HKD" wallet on the Deposit page -And I enter "1000000000" as the deposit amount -Then the deposit amount should be refused with "Please input an amount of limit max or below!" | G12: Valid UMPay credentials | H12: User should not be able to deposit amount greater than limit | I12: User is still on Deposit page | J12: User can not deposit amount greater than limit | K12: PASS | L12: HIGH | M12: KIMA | O12: Window OS | P12: Edge | S12: Run
A13: TC_005 | B13: Deposit | C13: The minimum itself is accepted | D13: Positive | E13: User is on Deposit page | F13: -I log into the UMPay application with valid email credentials using "1" of "sheet1" of "Deposit_TestData.xlsx" -When I navigate to Deposit page -And I choose the "HKD" wallet on the Deposit page -And I enter "100" as the deposit amount -Then the deposit amount should be accepted | G13: Valid UMPay credentials | H13: User should be able to perform deposit successfully | I13: User is navigated back to home screen | J13: User can perform deposit successfully | K13: PASS | L13: HIGH | M13: KIMA | O13: Window OS | P13: Edge | S13: Run
A14: TC_006 | B14: Deposit | C14: The amount box states the limits it enforces | D14: Positive | E14: User is on Deposit page | F14: -I log into the UMPay application with valid email credentials using "1" of "sheet1" of "Deposit_TestData.xlsx" -When I navigate to Deposit page -And I choose the "HKD" wallet on the Deposit page -Then the deposit form should state a minimum of "100" and a maximum of "999999999" | G14: Valid UMPay credentials | H14: User should be able to perform deposit successfully | I14: User is navigated back to home screen | J14: User can perform deposit successfully | K14: PASS | L14: HIGH | M14: KIMA | O14: Window OS | P14: Edge | S14: Run

Sheet Withdraw
A1: Project Name | B1: UMPay
A2: Module/Feature Name | B2: Withdraw | P2: HIGH | Q2: MEDIUM | R2: LOW
A3: Reference Document | N3: PASS | O3: =COUNTIF(K:K,"PASS") | P3: =COUNTIFS(K:K,"PASS",L:L,"HIGH") | Q3: =COUNTIFS(K:K,"PASS",L:L,"MEDIUM") | R3: =COUNTIFS(K:K,"PASS",L:L,"LOW")
A4: Created By | B4: KIMA | N4: FAIL | O4: =COUNTIF(K:K,"FAIL") | P4: =COUNTIFS(K:K,"FAIL",L:L,"HIGH") | Q4: =COUNTIFS(K:K,"FAIL",L:L,"MEDIUM") | R4: =COUNTIFS(K:K,"FAIL",L:L,"LOW")
A5: Date of Creation | B5: 46170 | N5: PENDING | O5: =COUNTIF(K:K,"PENDING") | P5: =COUNTIFS(K:K,"PENDING",L:L,"HIGH") | Q5: =COUNTIFS(K:K,"PENDING",L:L,"MEDIUM") | R5: =COUNTIFS(K:K,"PENDING",L:L,"LOW")
A6: Date of Review | B6: 46170
A8: TEST CASE ID | B8: TEST SCENARIO | C8: TEST CASE | D8: TEST CATEGORY | E8: PRE-CONDITION | F8: TEST STEPS | G8: TEST DATA | H8: EXPECTED RESULTS | I8: POST CONDITION | J8: ACTUAL RESULT | K8: STATUS | L8: PRIORITY | M8: TESTER | N8: TEST DATE | O8: DEVICE | P8: BROWSER | Q8: ISSUE LINK | R8: COMMENT | S8: Run
A9: TC_001 | B9: Withdraw | C9: Successful Withdraw Transaction using Template | D9: Positive | E9: User is on Withdraw page | F9: -Given I log into the UMPay application with valid email credentials using "<row>" of "<excelSheetName>" of "<excelFileName>" -When I navigate to Withdraw page -Then I should be able to initiate a withdraw transaction using "<row>" of "<excelSheetName>" of "<excelFileName>" | G9: Valid UNCS Admin credentials. | H9: User should be able to submit withdraw transaction successfully | I9: User is navigated to home page | J9: User can submit withdraw transaction successfully | K9: PASS | L9: HIGH | M9: KIMA | O9: Window OS | P9: Edge | S9: Run
A10: TC_002 | B10: Withdraw | C10: Successful Withdraw Transaction using New Account | D10: Positive | E10: User is on Withdraw page | F10: -Given I log into the UMPay application with valid email credentials using "<row>" of "<excelSheetName>" of "<excelFileName>" -When I navigate to Withdraw page -Then I should be able to initiate a withdraw transaction using "<row>" of "<excelSheetName>" of "<excelFileName>" | G10: Valid UNCS Admin credentials. | H10: User should be able to submit withdraw transaction successfully | I10: User is navigated to home page | J10: User can submit withdraw transaction successfully | K10: PASS | L10: HIGH | M10: KIMA | O10: Window OS | P10: Edge | S10: Run
A11: TC_003 | B11: Withdraw | C11: The withdraw form offers a wallet for every currency the account holds | D11: Positive | E11: User is on Withdraw page | F11: -Given I log into the UMPay application with valid email credentials using "<row>" of "<excelSheetName>" of "<excelFileName>" -When I navigate to Withdraw page -Then the withdraw currency list should offer "BDT, BRL, HKD, IDR, MXN, MYR, PHP, THB, USD, VND" | G11: Valid UNCS Admin credentials. | H11: User should be able to see all the wallets | I11: User is still on Withdraw page | J11: User can see all the wallets | K11: PASS | L11: HIGH | M11: KIMA | O11: Window OS | P11: Edge | S11: Run
A12: TC_004 | B12: Withdraw | C12: The amount box holds each wallet to its own stated limits | D12: Positive | E12: User is on Withdraw page | F12: -Given I log into the UMPay application with valid email credentials using "1" of "sheet1" of "Withdraw_TestData.xlsx" -When I navigate to Withdraw page -And I choose the "<currency>" wallet on the Withdraw page -And I enter one below the stated minimum as the withdraw amount -Then the withdraw amount should be refused with "Please input an amount of limit min or above!" -When I enter one above the stated maximum as the withdraw amount -Then the withdraw amount should be refused with "Please input an amount of limit max or below!" -When I enter the stated minimum as the withdraw amount -Then the withdraw amount should be accepted | G12: Valid UNCS Admin credentials. | H12: Amount limits should work as expected | I12: User is still on Withdraw page | J12: Amount limits are working as expected | K12: PASS | L12: HIGH | M12: KIMA | O12: Window OS | P12: Edge | S12: Run
A13: TC_005 | B13: Withdraw | C13: The amount box refuses anything that is not an amount | D13: Negative | E13: User is on the Withdraw page with the HKD wallet chosen | F13: -Given I log into the UMPay application with valid email credentials using "1" of "sheet1" of "Withdraw_TestData.xlsx" -When I navigate to Withdraw page -And I choose the "HKD" wallet on the Withdraw page -And I type "<typed>" at the withdraw amount box -Then the withdraw amount box should be left holding nothing -And the withdraw amount should be refused with "This field is required" | G13: Amount: abcd, 0, -100 | H13: None of these should be accepted as an amount, and the form should say the field is required rather than leaving something unpayable sitting in the box | I13: User is on the Withdraw page | J13: None of the three ever reached the box. "abcd", "0" and "-100" each left it holding nothing at all, and the form answered "This field is required" - so the form works on the box as it is typed rather than letting a wrong amount sit in it | K13: PASS | L13: HIGH | M13: KIMA | N13: 46273 | O13: Window OS | P13: Chromium | S13: Run
A14: TC_006 | B14: Withdraw | C14: The amount box will not take a figure finer than the currency pays in | D14: Negative | E14: User is on the Withdraw page with the HKD wallet chosen | F14: -Given I log into the UMPay application with valid email credentials using "1" of "sheet1" of "Withdraw_TestData.xlsx" -When I navigate to Withdraw page -And I choose the "HKD" wallet on the Withdraw page -And I type "<typed>" at the withdraw amount box -Then the withdraw amount box should be left holding "<kept>" | G14: Amount: 100.555 | H14: The box should keep only what the currency can be paid in - Hong Kong dollars have cents and nothing smaller | I14: User is on the Withdraw page | J14: Typing 100.555 left the box holding 100.55, so the form keeps only what Hong Kong dollars can actually be paid in | K14: PASS | L14: MEDIUM | M14: KIMA | N14: 46273 | O14: Window OS | P14: Chromium | S14: Run
A15: TC_007 | B15: Withdraw | C15: A withdraw cannot be confirmed with nowhere to send the money | D15: Negative | E15: User is on the Withdraw page with the HKD wallet chosen | F15: -Given I log into the UMPay application with valid email credentials using "1" of "sheet1" of "Withdraw_TestData.xlsx" -When I navigate to Withdraw page -And I choose the "<currency>" wallet on the Withdraw page -And I enter the stated minimum as the withdraw amount -Then the withdraw should not be confirmable -When I choose the saved payout account "<account>" -Then the withdraw should be confirmable | G15: Amount: the stated minimum; Payout account: none, then HSBC | H15: Confirm should not be pressable while no payout account has been chosen, and choosing one should be what makes it pressable | I15: User is on the Withdraw page | J15: With 100 HKD entered and no payout account chosen, Confirm was disabled and could not be pressed. Choosing the saved HSBC account is what made it pressable, so the payout account is what was stopping it rather than something else on the form | K15: PASS | L15: HIGH | M15: KIMA | N15: 46273 | O15: Window OS | P15: Chromium | S15: Run
A16: TC_008 | B16: Withdraw | C16: A withdraw for more than the wallet holds is refused | D16: Negative | E16: User is on the Withdraw page with the HKD wallet chosen | F16: -Given I log into the UMPay application with valid email credentials using "1" of "sheet1" of "Withdraw_TestData.xlsx" -When I navigate to Withdraw page -And I choose the "<currency>" wallet on the Withdraw page -And I enter more than the wallet holds as the withdraw amount -And I choose the saved payout account "<account>" -And I confirm the withdraw -Then the platform should refuse to raise the order | G16: Amount: a thousand more than the wallet holds; Payout account: HSBC | H16: The platform should refuse to raise the order and say why, so somebody withdrawing from their own wallet is told they are short rather than left pressing Confirm | I16: No order is raised and the wallet is untouched | J16: DEFECT - the HKD wallet held HK$8,156.51 and the form was asked for 9,156 with the saved HSBC account chosen. Confirm was enabled, it was pressed, and then nothing happened at all: no PIN was asked for, no order was raised, no dialog, no notice, no message of any kind. The network confirms nothing was even attempted - the last call the page made was the fee lookup /api/fee/payment/PM134081?currency=HKD&amount=9156, and no withdraw was ever posted. The money is safe, but somebody withdrawing from their own wallet is left pressing a button that silently does nothing and is never told they are short | K16: FAIL | L16: HIGH | M16: KIMA | N16: 46273 | O16: Window OS | P16: Chromium | S16: Run

Sheet Transfer
A1: Project Name | B1: UMPay
A2: Module/Feature Name | B2: Transfer | P2: HIGH | Q2: MEDIUM | R2: LOW
A3: Reference Document | N3: PASS | O3: =COUNTIF(K:K,"PASS") | P3: =COUNTIFS(K:K,"PASS",L:L,"HIGH") | Q3: =COUNTIFS(K:K,"PASS",L:L,"MEDIUM") | R3: =COUNTIFS(K:K,"PASS",L:L,"LOW")
A4: Created By | B4: KIMA | N4: FAIL | O4: =COUNTIF(K:K,"FAIL") | P4: =COUNTIFS(K:K,"FAIL",L:L,"HIGH") | Q4: =COUNTIFS(K:K,"FAIL",L:L,"MEDIUM") | R4: =COUNTIFS(K:K,"FAIL",L:L,"LOW")
A5: Date of Creation | B5: 46170 | N5: PENDING | O5: =COUNTIF(K:K,"PENDING") | P5: =COUNTIFS(K:K,"PENDING",L:L,"HIGH") | Q5: =COUNTIFS(K:K,"PENDING",L:L,"MEDIUM") | R5: =COUNTIFS(K:K,"PENDING",L:L,"LOW")
A6: Date of Review | B6: 46170
A8: TEST CASE ID | B8: TEST SCENARIO | C8: TEST CASE | D8: TEST CATEGORY | E8: PRE-CONDITION | F8: TEST STEPS | G8: TEST DATA | H8: EXPECTED RESULTS | I8: POST CONDITION | J8: ACTUAL RESULT | K8: STATUS | L8: PRIORITY | M8: TESTER | N8: TEST DATE | O8: DEVICE | P8: BROWSER | Q8: ISSUE LINK | R8: COMMENT | S8: Run
A9: TC_001 | B9: Transfer | C9: The Transfer hub offers all different types of transfer options | D9: Positive | E9: User is on Transfer page | F9: -Given I log into the UMPay application with valid email credentials using "<row>" of "<excelSheetName>" of "<excelFileName>" -When I open the Transfer hub -Then the Transfer hub should offer the route "UMPay to Existing template" -And the Transfer hub should offer the route "UMPay to UMPay Wallet" -And the Transfer hub should offer the route "UnionPay China" -And the Transfer hub should offer the route "UnionPay Global" -And the Transfer hub should offer the route "Transfer to Alipay" -And the Transfer hub should offer the route "Transfer to Wechat" | G9: Valid UMPay User | H9: User should be able to see all options | I9: User is still on Transfer page | J9: User can see all options | K9: PASS | L9: HIGH | M9: KIMA | O9: Window OS | P9: Edge | S9: Run
A10: TC_002 | B10: Transfer | C10: A payment option under maintenance should not open | D10: Positive | E10: User is on Transfer page | F10: -Given I log into the UMPay application with valid email credentials using "1" of "sheet1" of "Transfer_TestData.xlsx" -When I open the Transfer hub -Then the route "<route>" should be marked as under maintenance -When I take the "<route>" route from the Transfer hub -Then the app should say the service is unavailable | G10: Valid UMPay User | H10: User should not be able to open payment option under maintenance | I10: User is still on Transfer page | J10: User can not open payment option under maintenance | K10: PASS | L10: HIGH | M10: KIMA | O10: Window OS | P10: Edge | S10: Run
A11: TC_003 | B11: Transfer | C11: A wallet transfer cannot go forward from an empty form | D11: Negative | E11: User is on Transfer page | F11: -Given I log into the UMPay application with valid email credentials using "<row>" of "<excelSheetName>" of "<excelFileName>" -When I open the Transfer hub -And I take the "UMPay to UMPay Wallet" route from the Transfer hub -Then the UMPay wallet transfer form should be shown -And the wallet transfer should not be ready to continue | G11: Valid UMPay User | H11: User should not be able to perform transfer | I11: User is still on Transfer page | J11: User can not perform transfer | K11: PASS | L11: HIGH | M11: KIMA | O11: Window OS | P11: Edge | S11: Run
A12: TC_004 | B12: Transfer | C12: A wallet transfer is refused when nobody holds the mobile number | D12: Negative | E12: User is on Transfer page | F12: -Given I log into the UMPay application with valid email credentials using "<row>" of "<excelSheetName>" of "<excelFileName>" -When I open the Transfer hub -And I take the "UMPay to UMPay Wallet" route from the Transfer hub -Then the UMPay wallet transfer form should be shown -And the wallet form should keep the amount and remark locked -When I give the recipient's phone number in "<row>" of "<excelSheetName>" of "<excelFileName>" -Then the form should say the recipient does not exist -And the wallet form should keep the amount and remark locked -And the wallet transfer should not be ready to continue | G12: Valid UMPay User | H12: User should not be able to perform transfer | I12: User is still on Transfer page | J12: User can not perform transfer | K12: PASS | L12: HIGH | M12: KIMA | O12: Window OS | P12: Edge | S12: Run
A13: TC_005 | B13: Transfer | C13: A recipient nobody holds is refused when named by ID | D13: Negative | E13: User is on Transfer page | F13: -Given I log into the UMPay application with valid email credentials using "<row>" of "<excelSheetName>" of "<excelFileName>" -When I open the Transfer hub -And I take the "UMPay to UMPay Wallet" route from the Transfer hub -Then the UMPay wallet transfer form should be shown -When I name the recipient by "ID" -And I give the recipient's "ID" from "<row>" of "<excelSheetName>" of "<excelFileName>" -Then the form should say the recipient does not exist -And the wallet form should keep the amount and remark locked -And the wallet transfer should not be ready to continue | G13: Valid UMPay User | H13: User should not be able to perform transfer | I13: User is still on Transfer page | J13: User can not perform transfer | K13: PASS | L13: HIGH | M13: KIMA | O13: Window OS | P13: Edge | S13: Run
A14: TC_006 | B14: Transfer | C14: A recipient nobody holds is refused when named by Email | D14: Negative | E14: User is on Transfer page | F14: -Given I log into the UMPay application with valid email credentials using "<row>" of "<excelSheetName>" of "<excelFileName>" -When I open the Transfer hub -And I take the "UMPay to UMPay Wallet" route from the Transfer hub -Then the UMPay wallet transfer form should be shown -When I name the recipient by "EMAIL" -And I give the recipient's "EMAIL" from "<row>" of "<excelSheetName>" of "<excelFileName>" -Then the form should say the recipient does not exist -And the wallet form should keep the amount and remark locked -And the wallet transfer should not be ready to continue | G14: Valid UMPay User | H14: User should not be able to perform transfer | I14: User is still on Transfer page | J14: User can not perform transfer | K14: PASS | L14: HIGH | M14: KIMA | O14: Window OS | P14: Edge | S14: Run
A15: TC_007 | B15: Transfer | C15: A wallet transfer is sent to a recipient named by ID | D15: Positive | E15: User is on Transfer page | F15: -Given I log into the UMPay application with valid email credentials using "<row>" of "<excelSheetName>" of "<excelFileName>" -When I open the Transfer hub -And I take the "UMPay to UMPay Wallet" route from the Transfer hub -Then the UMPay wallet transfer form should be shown -And the wallet form should keep the amount and remark locked -When I name the recipient by "ID" -And I give the recipient's "ID" from "<row>" of "<excelSheetName>" of "<excelFileName>" -Then the form should find the recipient -When I enter the amount in "<row>" of "<excelSheetName>" of "<excelFileName>" to send -Then the wallet transfer should be ready to continue -When I send the wallet transfer, which moves real money -Then the wallet transfer should go through | G15: Valid UMPay User | H15: User should be able to perform transfer | I15: User is still on Transfer page | J15: User can perform transfer | K15: PASS | L15: HIGH | M15: KIMA | O15: Window OS | P15: Edge | S15: Run
A16: TC_008 | B16: Transfer | C16: A wallet transfer is sent to a recipient named by Email | D16: Positive | E16: User is on Transfer page | F16: -Given I log into the UMPay application with valid email credentials using "<row>" of "<excelSheetName>" of "<excelFileName>" -When I open the Transfer hub -And I take the "UMPay to UMPay Wallet" route from the Transfer hub -Then the UMPay wallet transfer form should be shown -And the wallet form should keep the amount and remark locked -When I name the recipient by "EMAIL" -And I give the recipient's "EMAIL" from "<row>" of "<excelSheetName>" of "<excelFileName>" -Then the form should find the recipient -When I enter the amount in "<row>" of "<excelSheetName>" of "<excelFileName>" to send -Then the wallet transfer should be ready to continue -When I send the wallet transfer, which moves real money -Then the wallet transfer should go through | G16: Valid UMPay User | H16: User should be able to perform transfer | I16: User is still on Transfer page | J16: User can perform transfer | K16: PASS | L16: HIGH | M16: KIMA | O16: Window OS | P16: Edge | S16: Run
A17: TC_009 | B17: Transfer | C17: A wallet transfer is sent to a recipient named by Mobile | D17: Positive | E17: User is on Transfer page | F17: -Given I log into the UMPay application with valid email credentials using "<row>" of "<excelSheetName>" of "<excelFileName>" -When I open the Transfer hub -And I take the "UMPay to UMPay Wallet" route from the Transfer hub -Then the UMPay wallet transfer form should be shown -And the wallet form should keep the amount and remark locked -When I name the recipient by "MOBILE" -And I give the recipient's "MOBILE" from "<row>" of "<excelSheetName>" of "<excelFileName>" -Then the form should find the recipient -When I enter the amount in "<row>" of "<excelSheetName>" of "<excelFileName>" to send -Then the wallet transfer should be ready to continue -When I send the wallet transfer, which moves real money -Then the wallet transfer should go through | G17: Valid UMPay User | H17: User should be able to perform transfer | I17: User is still on Transfer page | J17: User can perform transfer | K17: PASS | L17: HIGH | M17: KIMA | O17: Window OS | P17: Edge | S17: Run
A18: TC_010 | B18: Transfer | C18: A UnionPay China transfer from the Transfer page converts and is sent | D18: Positive | E18: User is on Transfer page | F18: -Given I log into the UMPay application with valid email credentials using "<row>" of "<excelSheetName>" of "<excelFileName>" -When I open the Transfer hub -And I take the "UnionPay China" route from the Transfer hub -Then the UnionPay amount form should be shown -And the UnionPay form should state "Limit Min" -And the UnionPay form should state "Limit Max" -And the UnionPay form should offer a converted amount -When I enter the stated minimum as the UnionPay amount -Then the converted amount should be worked out -And the UnionPay transfer should be ready to continue -When I go on to the receiver step -And I send it to the saved receiver in "<row>" of "<excelSheetName>" of "<excelFileName>", which moves real money -Then the transfer should go through | G18: Valid UMPay User | H18: User should be able to perform transfer | I18: User is still on Transfer page | J18: User can perform transfer | K18: PASS | L18: HIGH | M18: KIMA | O18: Window OS | P18: Edge | S18: Run
A19: TC_011 | B19: Transfer | C19: A UnionPay Global transfer from the Transfer page does not convert and is sent | D19: Positive | E19: User is on Transfer page | F19: -Given I log into the UMPay application with valid email credentials using "<row>" of "<excelSheetName>" of "<excelFileName>" -When I open the Transfer hub -And I take the "UnionPay Global" route from the Transfer hub -Then the UnionPay amount form should be shown -And the UnionPay form should state "Limit Min" -And the UnionPay form should state "Limit Max" -And the UnionPay form should not offer a converted amount -When I enter the stated minimum as the UnionPay amount -Then the UnionPay transfer should be ready to continue -When I go on to the receiver step -And I send it to the saved receiver in "<row>" of "<excelSheetName>" of "<excelFileName>", which moves real money -Then the transfer should go through | G19: Valid UMPay User | H19: User should be able to perform transfer | I19: User is still on Transfer page | J19: User can perform transfer | K19: PASS | L19: HIGH | M19: KIMA | O19: Window OS | P19: Edge | S19: Run
A20: TC_012 | B20: Transfer | C20: The Existing template route lists the destinations saved on the account | D20: Positive | E20: User is on Transfer page | F20: -Given I log into the UMPay application with valid email credentials using "<row>" of "<excelSheetName>" of "<excelFileName>" -When I open the Transfer hub -And I take the "UMPay to Existing template" route from the Transfer hub -Then the saved templates should be listed -And every saved template should mask the account it pays | G20: Valid UMPay User | H20: User should be able to see templates | I20: User is still on Transfer page | J20: User can see templates | K20: PASS | L20: HIGH | M20: KIMA | O20: Window OS | P20: Edge | S20: Run
A21: TC_013 | B21: Transfer | C21: A transfer to a saved template is sent | D21: Positive | E21: User is on Transfer page | F21: -Given I log into the UMPay application with valid email credentials using "<row>" of "<excelSheetName>" of "<excelFileName>" -When I open the Transfer hub -And I take the "UMPay to Existing template" route from the Transfer hub -Then the saved templates should be listed -When I choose the saved template in "<row>" of "<excelSheetName>" of "<excelFileName>" -Then the UnionPay amount form should be shown -And the transfer should be going to the account in "<row>" of "<excelSheetName>" of "<excelFileName>" -When I enter the stated minimum as the UnionPay amount -And I send the transfer, which moves real money -Then the transfer should be accepted | G21: Valid UMPay User | H21: User should be able to see templates | I21: User is still on Transfer page | J21: User can see templates | K21: PASS | L21: HIGH | M21: KIMA | O21: Window OS | P21: Edge | S21: Run

Sheet Convert
A1: Project Name | B1: UMPay
A2: Module/Feature Name | B2: Transfer | P2: HIGH | Q2: MEDIUM | R2: LOW
A3: Reference Document | N3: PASS | O3: =COUNTIF(K:K,"PASS") | P3: =COUNTIFS(K:K,"PASS",L:L,"HIGH") | Q3: =COUNTIFS(K:K,"PASS",L:L,"MEDIUM") | R3: =COUNTIFS(K:K,"PASS",L:L,"LOW")
A4: Created By | B4: KIMA | N4: FAIL | O4: =COUNTIF(K:K,"FAIL") | P4: =COUNTIFS(K:K,"FAIL",L:L,"HIGH") | Q4: =COUNTIFS(K:K,"FAIL",L:L,"MEDIUM") | R4: =COUNTIFS(K:K,"FAIL",L:L,"LOW")
A5: Date of Creation | B5: 46170 | N5: PENDING | O5: =COUNTIF(K:K,"PENDING") | P5: =COUNTIFS(K:K,"PENDING",L:L,"HIGH") | Q5: =COUNTIFS(K:K,"PENDING",L:L,"MEDIUM") | R5: =COUNTIFS(K:K,"PENDING",L:L,"LOW")
A6: Date of Review | B6: 46170
A8: TEST CASE ID | B8: TEST SCENARIO | C8: TEST CASE | D8: TEST CATEGORY | E8: PRE-CONDITION | F8: TEST STEPS | G8: TEST DATA | H8: EXPECTED RESULTS | I8: POST CONDITION | J8: ACTUAL RESULT | K8: STATUS | L8: PRIORITY | M8: TESTER | N8: TEST DATE | O8: DEVICE | P8: BROWSER | Q8: ISSUE LINK | R8: COMMENT | S8: Run
A9: TC_001 | B9: Convert | C9: Money is converted between two wallets | D9: Positive | E9: User is on Admin Team Page. | F9: -Given I log into the UMPay application with valid email credentials using "<row>" of "<excelSheetName>" of "<excelFileName>" -When I navigate to the Convert page -And I convert the amount in "<row>" of "<excelSheetName>" of "<excelFileName>" -Then the conversion should be confirmed with the message in "<row>" of "<excelSheetName>" of "<excelFileName>" -And the source wallet balance should have gone down by the converted amount | G9: Valid UMPay user | H9: User should be able to convert money between wallets | I9: User is still on convert page | J9: User can convert money between wallets | K9: PASS | L9: HIGH | M9: KIMA | O9: Window OS | P9: Edge | S9: Run
A10: TC_002 | B10: Convert | C10: Every wallet converts into every other wallet | D10: Positive | E10: User is on Admin Team Page. | F10: -Given I log into the UMPay application with valid email credentials using "<row>" of "<excelSheetName>" of "<excelFileName>" -When I navigate to the Convert page -Then converting the amount in "<row>" of "<excelSheetName>" of "<excelFileName>" into every other wallet, ending with "HKD", should succeed | G10: Valid UMPay user | H10: User should be able to convert money between each wallet pair | I10: User is still on convert page | J10: User can convert money between each wallet pair | K10: PASS | L10: HIGH | M10: KIMA | O10: Window OS | P10: Edge | S10: Run
A11: TC_003 | B11: Convert | C11: The convert form offers a wallet for every currency the account holds | D11: Positive | E11: User is on Admin Team Page. | F11: -Given I log into the UMPay application with valid email credentials using "<row>" of "<excelSheetName>" of "<excelFileName>" -When I navigate to the Convert page -Then the convert currency list should offer "BDT, BRL, HKD, IDR, MXN, MYR, PHP, THB, USD, VND" | G11: Valid UMPay user | H11: User should be able to see all wallets | I11: User is still on convert page | J11: User can all wallets | K11: PASS | L11: HIGH | M11: KIMA | O11: Window OS | P11: Edge | S11: Run
A12: TC_004 | B12: Convert | C12: The amount box holds a conversion to the pair's stated limits | D12: Positive | E12: User is on Admin Team Page. | F12: -GGiven I log into the UMPay application with valid email credentials using "<row>" of "<excelSheetName>" of "<excelFileName>" -When I navigate to the Convert page -And I choose to convert from "HKD" to "PHP" -And I enter one below the stated minimum as the convert amount -Then the convert amount should be refused with "Please input an amount of limit min or above!" -When I enter one above the stated maximum as the convert amount -Then the convert amount should be refused with "Please input an amount of limit max or below!" -When I enter the stated minimum as the convert amount -Then the convert amount should be accepted -And the form should offer to convert | G12: Valid UMPay user | H12: All the set limits should work as expected | I12: User is still on convert page | J12: All the set limits are working as expected | K12: PASS | L12: HIGH | M12: KIMA | O12: Window OS | P12: Edge | S12: Run
A13: TC_005 | B13: Convert | C13: The conversion history opens from the Convert page | D13: Positive | E13: User is on Admin Team Page. | F13: -Given I log into the UMPay application with valid email credentials using "<row>" of "<excelSheetName>" of "<excelFileName>" -When I navigate to the Convert page -And I open the conversion history -Then the conversion history should be shown -And every conversion listed should name an amount, a time, what it became and the rate | G13: Valid UMPay user | H13: User should be able to access history | I13: User is still on convert page | J13: User can access history | K13: PASS | L13: HIGH | M13: KIMA | O13: Window OS | P13: Edge | S13: Run
A14: TC_006 | B14: Convert | C14: A latest conversion appears at the top of the history | D14: Positive | E14: User is on Admin Team Page. | F14: -Given I log into the UMPay application with valid email credentials using "<row>" of "<excelSheetName>" of "<excelFileName>" -When I navigate to the Convert page -And I convert the amount in "<row>" of "<excelSheetName>" of "<excelFileName>" -Then the conversion should be confirmed with the message in "<row>" of "<excelSheetName>" of "<excelFileName>" -When I open the conversion history -Then the conversion history should be shown -And the newest entry should be the conversion just made in "<row>" of "<excelSheetName>" of "<excelFileName>" | G14: Valid UMPay user | H14: Latest conversion should appear at the top | I14: User is still on convert page | J14: Latest conversion appears at the top | K14: PASS | L14: HIGH | M14: KIMA | O14: Window OS | P14: Edge | S14: Run
A15: TC_007 | B15: Convert | C15: Each conversion receipt in the history can be opened | D15: Positive | E15: User is on Admin Team Page. | F15: -Given I log into the UMPay application with valid email credentials using "<row>" of "<excelSheetName>" of "<excelFileName>" -When I navigate to the Convert page -And I open the conversion history -Then the conversion history should be shown -And each of the first 3 conversions should open a receipt that matches its entry | G15: Valid UMPay user | H15: User should be able to open each conversion history receipt | I15: User is still on convert page | J15: Usercan open each conversion history receipt | K15: PASS | L15: HIGH | M15: KIMA | O15: Window OS | P15: Edge | S15: Run
A16: TC_008 | B16: Convert | C16: A receipt displays what was converted, what it became, the rate and when | D16: Positive | E16: User is on Admin Team Page. | F16: -Given I log into the UMPay application with valid email credentials using "<row>" of "<excelSheetName>" of "<excelFileName>" -When I navigate to the Convert page -And I open the conversion history -And I open the newest conversion -Then the receipt should name what was converted, what it became, the rate and when | G16: Valid UMPay user | H16: Each receipt should display details correctly | I16: User is still on convert page | J16: Each receipt displays details correctly | K16: PASS | L16: HIGH | M16: KIMA | O16: Window OS | P16: Edge | S16: Run
A17: TC_009 | B17: Convert | C17: A receipt can be downloaded | D17: Positive | E17: User is on Admin Team Page. | F17: -Given I log into the UMPay application with valid email credentials using "<row>" of "<excelSheetName>" of "<excelFileName>" -When I navigate to the Convert page -And I open the conversion history -And I open the newest conversion -Then downloading the receipt should produce a file | G17: Valid UMPay user | H17: User should be able to download a receipt | I17: User is still on convert page | J17: User can download a receipt | K17: PASS | L17: HIGH | M17: KIMA | O17: Window OS | P17: Edge | S17: Run
A18: TC_010 | B18: Convert | C18: A receipt can be shared | D18: Positive | E18: User is on Admin Team Page. | F18: -Given I log into the UMPay application with valid email credentials using "<row>" of "<excelSheetName>" of "<excelFileName>" -When I navigate to the Convert page -And I open the conversion history -And I open the newest conversion -When I share the receipt -Then the sharing choices should offer a way to copy it | G18: Valid UMPay user | H18: User should be able to share a receipt | I18: User is still on convert page | J18: User can share a receipt | K18: PASS | L18: HIGH | M18: KIMA | O18: Window OS | P18: Edge | S18: Run
A19: TC_011 | B19: Convert | C19: More than the wallet holds cannot be converted | D19: Negative | E19: User is on the Convert page converting HKD to PHP | F19: -Given I log into the UMPay application with valid email credentials using "<row>" of "<excelSheetName>" of "<excelFileName>" -When I navigate to the Convert page -And I choose to convert from "HKD" to "PHP" -And I enter more than the wallet holds as the convert amount -Then the convert amount should be accepted -But the form should not offer to convert | G19: Amount: one more than the wallet holds | H19: The form should take the figure into the box but refuse to convert it, since the wallet cannot cover it | I19: Nothing is converted | J19: The HKD wallet held 7,943.51 and the form was asked to convert 7,944.51. The box took the figure and Convert stayed disabled, so the conversion could not be started | K19: PASS | L19: HIGH | M19: KIMA | N19: 46273 | O19: Window OS | P19: Chromium | S19: Run

Sheet International_School_Fee
A1: Project Name | B1: UMPay
A2: Module/Feature Name | B2: International School Fee | P2: HIGH | Q2: MEDIUM | R2: LOW
A3: Reference Document | N3: PASS | O3: =COUNTIF(K:K,"PASS") | P3: =COUNTIFS(K:K,"PASS",L:L,"HIGH") | Q3: =COUNTIFS(K:K,"PASS",L:L,"MEDIUM") | R3: =COUNTIFS(K:K,"PASS",L:L,"LOW")
A4: Created By | B4: KIMA | N4: FAIL | O4: =COUNTIF(K:K,"FAIL") | P4: =COUNTIFS(K:K,"FAIL",L:L,"HIGH") | Q4: =COUNTIFS(K:K,"FAIL",L:L,"MEDIUM") | R4: =COUNTIFS(K:K,"FAIL",L:L,"LOW")
A5: Date of Creation | B5: 46170 | N5: PENDING | O5: =COUNTIF(K:K,"PENDING") | P5: =COUNTIFS(K:K,"PENDING",L:L,"HIGH") | Q5: =COUNTIFS(K:K,"PENDING",L:L,"MEDIUM") | R5: =COUNTIFS(K:K,"PENDING",L:L,"LOW")
A6: Date of Review | B6: 46170
A8: TEST CASE ID | B8: TEST SCENARIO | C8: TEST CASE | D8: TEST CATEGORY | E8: PRE-CONDITION | F8: TEST STEPS | G8: TEST DATA | H8: EXPECTED RESULTS | I8: POST CONDITION | J8: ACTUAL RESULT | K8: STATUS | L8: PRIORITY | M8: TESTER | N8: TEST DATE | O8: DEVICE | P8: BROWSER | Q8: ISSUE LINK | R8: COMMENT | S8: Run
A9: TC_001 | B9: International School Fee | C9: A school fee is paid to a school typed in for the first time | D9: Positive | E9: User is on International School Fee Page. | F9: -Given I log into the UMPay application with valid email credentials using "<row>" of "<excelSheetName>" of "<excelFileName>" -When I open International School Fees from the sidebar -Then the school fee form should be shown -When I enter the stated minimum as the school fee amount -Then the form should work out the fee and what it comes to -When I go on from the school fee amount -Then the form should ask which school is being paid -When I enter the school details in "<row>" of "<excelSheetName>" of "<excelFileName>" -Then the school fee should be ready to send -When I send the school fee, which moves real money -Then the school fee should go through | G9: Valid UMPay user | H9: User should be able to transfer school fee for new entry | I9: User is still on International School Fee page | J9: User can transfer school fee for new entry | K9: PASS | L9: HIGH | M9: KIMA | O9: Window OS | P9: Edge | S9: Run
A10: TC_002 | B10: International School Fee | C10: A school fee is paid to a saved school | D10: Positive | E10: User is on International School Fee Page. | F10: -Given I log into the UMPay application with valid email credentials using "<row>" of "<excelSheetName>" of "<excelFileName>" -When I open International School Fees from the sidebar -Then the school fee form should be shown -When I enter the stated minimum as the school fee amount -Then the form should work out the fee and what it comes to -When I go on from the school fee amount -Then the form should ask which school is being paid -When I open the schools saved on the account -And I choose the school saved in "<row>" of "<excelSheetName>" of "<excelFileName>" -Then the school and the student should be filled in from "<row>" of "<excelSheetName>" of "<excelFileName>" -When I send the school fee, which moves real money -Then the school fee should go through | G10: Valid UMPay user | H10: User should be able to transfer school fee for templates | I10: User is still on International School Fee page | J10: User can transfer school fee for templates | K10: PASS | L10: HIGH | M10: KIMA | O10: Window OS | P10: Edge | S10: Run
A11: TC_003 | B11: International School Fee | C11: Less than the stated minimum amount can not be sent | D11: Negative | E11: User is on International School Fee Page. | F11: -Given I log into the UMPay application with valid email credentials using "<row>" of "<excelSheetName>" of "<excelFileName>" -When I open International School Fees from the sidebar -Then the school fee form should be shown -When I enter one below the stated minimum as the school fee amount -And I go on from the school fee amount -Then the form should not go on, and should say nothing about why | G11: Valid UMPay user | H11: User should not be able to transfer school fee | I11: User is still on International School Fee page | J11: User can not transfer school fee | K11: PASS | L11: HIGH | M11: KIMA | O11: Window OS | P11: Edge | S11: Run
A12: TC_004 | B12: International School Fee | C12: The sidebar opens the school fee form | D12: Positive | E12: User is signed in | F12: -Given I log into the UMPay application with valid email credentials using "<row>" of "<excelSheetName>" of "<excelFileName>" -When I open International School Fees from the sidebar -Then the school fee form should be shown -And the school fee form should show the sending wallet and its balance -And the school fee form should ask for an amount and a remark | G12: Valid UMPay user | H12: International School Fees in the sidebar should open the school fee form | I12: User is on the school fee form | J12: The sidebar opened the school fee form | K12: PASS | L12: HIGH | M12: KIMA | N12: 46273 | O12: Window OS | P12: Chromium | S12: Run
A13: TC_005 | B13: International School Fee | C13: The form states the minimum it will take | D13: Positive | E13: User is on the school fee form | F13: -Given I log into the UMPay application with valid email credentials using "<row>" of "<excelSheetName>" of "<excelFileName>" -When I open International School Fees from the sidebar -Then the school fee form should be shown -And the school fee form should state the minimum recorded in "<row>" of "<excelSheetName>" of "<excelFileName>" | G13: Minimum: 100 USD | H13: The form should state the minimum it will take, and it should be the minimum on record - a minimum that moves without anybody noticing is what this case exists to catch | I13: User is on the school fee form | J13: The form states a minimum of 100 USD. It had been recorded as 10, and this case caught the platform having raised it; the sheet now records 100 | K13: PASS | L13: HIGH | M13: KIMA | N13: 46273 | O13: Window OS | P13: Chromium | S13: Run
A14: TC_006 | B14: International School Fee | C14: An empty form cannot go on | D14: Negative | E14: User is on the school fee form | F14: -Given I log into the UMPay application with valid email credentials using "<row>" of "<excelSheetName>" of "<excelFileName>" -When I open International School Fees from the sidebar -Then the school fee form should be shown -And the school fee transfer should not be ready to continue | G14: Nothing filled in | H14: An empty form should not be able to go on | I14: User is on the school fee form | J14: The empty form would not go on | K14: PASS | L14: HIGH | M14: KIMA | N14: 46273 | O14: Window OS | P14: Chromium | S14: Run
A15: TC_007 | B15: International School Fee | C15: The form works out the fee and what the transfer comes to | D15: Positive | E15: User is on the school fee form | F15: -Given I log into the UMPay application with valid email credentials using "<row>" of "<excelSheetName>" of "<excelFileName>" -When I open International School Fees from the sidebar -Then the school fee form should be shown -When I enter the stated minimum as the school fee amount -Then the form should work out the fee and what it comes to -And the school fee transfer should be ready to continue | G15: Amount: the stated minimum | H15: The form should work out the fee and what the transfer comes to, so somebody can see the cost before committing | I15: User is on the school fee form | J15: The form worked out the fee and what the transfer comes to | K15: PASS | L15: HIGH | M15: KIMA | N15: 46273 | O15: Window OS | P15: Chromium | S15: Run
A16: TC_008 | B16: International School Fee | C16: More than the wallet holds is carried past the amount step unchecked | D16: Negative | E16: User is on the school fee form | F16: -Given I log into the UMPay application with valid email credentials using "<row>" of "<excelSheetName>" of "<excelFileName>" -When I open International School Fees from the sidebar -Then the school fee form should be shown -When I enter more than the wallet holds as the school fee amount -Then the school fee transfer should be ready to continue -When I go on from the school fee amount -Then the form should ask which school is being paid | G16: Amount: more than the wallet holds | H16: What the form actually does with an amount larger than the wallet holds, recorded as it is rather than as it ought to be | I16: User is past the amount step | J16: The form carried an amount larger than the wallet holds past the amount step without checking it at all - which is what this case records. The check, if there is one, comes later | K16: PASS | L16: MEDIUM | M16: KIMA | N16: 46273 | O16: Window OS | P16: Chromium | S16: Run
A17: TC_009 | B17: International School Fee | C17: The amount step leads to choosing who is being paid | D17: Positive | E17: User is past the amount step | F17: -Given I log into the UMPay application with valid email credentials using "<row>" of "<excelSheetName>" of "<excelFileName>" -When I open International School Fees from the sidebar -Then the school fee form should be shown -When I enter the stated minimum as the school fee amount -And I go on from the school fee amount -Then the form should ask which school is being paid | G17: Amount: the stated minimum | H17: The amount step should lead on to choosing the school being paid | I17: User is choosing who is being paid | J17: The amount step led on to choosing who is being paid | K17: PASS | L17: MEDIUM | M17: KIMA | N17: 46273 | O17: Window OS | P17: Chromium | S17: Run
A18: TC_010 | B18: International School Fee | C18: The saved schools are offered | D18: Positive | E18: User is choosing who is being paid | F18: -Given I log into the UMPay application with valid email credentials using "<row>" of "<excelSheetName>" of "<excelFileName>" -When I open International School Fees from the sidebar -Then the school fee form should be shown -When I enter the stated minimum as the school fee amount -And I go on from the school fee amount -Then the form should ask which school is being paid -When I open the schools saved on the account -Then the schools saved on the account should be listed | G18: The schools this account has saved | H18: The schools the account has saved should be offered rather than typed in again | I18: User is choosing who is being paid | J18: The saved schools were offered | K18: PASS | L18: MEDIUM | M18: KIMA | N18: 46273 | O18: Window OS | P18: Chromium | S18: Run
A19: TC_011 | B19: International School Fee | C19: Choosing a saved school fills in the school and the student | D19: Positive | E19: User is choosing who is being paid | F19: -Given I log into the UMPay application with valid email credentials using "<row>" of "<excelSheetName>" of "<excelFileName>" -When I open International School Fees from the sidebar -Then the school fee form should be shown -When I enter the stated minimum as the school fee amount -And I go on from the school fee amount -Then the form should ask which school is being paid -When I open the schools saved on the account -Then the schools saved on the account should be listed -When I choose the school saved in "<row>" of "<excelSheetName>" of "<excelFileName>" -Then the school and the student should be filled in from "<row>" of "<excelSheetName>" of "<excelFileName>" | G19: A saved school | H19: Choosing a saved school should fill in both the school and the student it was saved against | I19: The school and student are filled in | J19: Choosing a saved school filled in both the school and the student | K19: PASS | L19: HIGH | M19: KIMA | N19: 46273 | O19: Window OS | P19: Chromium | S19: Run
A20: TC_012 | B20: International School Fee | C20: Global Transfer reaches the same form | D20: Positive | E20: User is in the Global Transfer area | F20: -Given I log into the UMPay application with valid email credentials using "<row>" of "<excelSheetName>" of "<excelFileName>" -When I open the Global Transfer area -And I take the "UMPay Transfer to School Fees" route from Global Transfer -Then the school fee form should be shown -And the school fee form should show the sending wallet and its balance -And the school fee form should ask for an amount and a remark | G20: Valid UMPay user | H20: Global Transfer should reach the same school fee form as the sidebar, rather than a second form that could drift from it | I20: User is on the school fee form | J20: Global Transfer reached the same school fee form | K20: PASS | L20: MEDIUM | M20: KIMA | N20: 46273 | O20: Window OS | P20: Chromium | S20: Run

Sheet Domestic_Transfer
A1: Project Name | B1: UMPay
A2: Module/Feature Name | B2: Domestic Transfer | P2: HIGH | Q2: MEDIUM | R2: LOW
A3: Reference Document | N3: PASS | O3: =COUNTIF(K:K,"PASS") | P3: =COUNTIFS(K:K,"PASS",L:L,"HIGH") | Q3: =COUNTIFS(K:K,"PASS",L:L,"MEDIUM") | R3: =COUNTIFS(K:K,"PASS",L:L,"LOW")
A4: Created By | B4: KIMA | N4: FAIL | O4: =COUNTIF(K:K,"FAIL") | P4: =COUNTIFS(K:K,"FAIL",L:L,"HIGH") | Q4: =COUNTIFS(K:K,"FAIL",L:L,"MEDIUM") | R4: =COUNTIFS(K:K,"FAIL",L:L,"LOW")
A5: Date of Creation | B5: 46170 | N5: PENDING | O5: =COUNTIF(K:K,"PENDING") | P5: =COUNTIFS(K:K,"PENDING",L:L,"HIGH") | Q5: =COUNTIFS(K:K,"PENDING",L:L,"MEDIUM") | R5: =COUNTIFS(K:K,"PENDING",L:L,"LOW")
A6: Date of Review | B6: 46170
A8: TEST CASE ID | B8: TEST SCENARIO | C8: TEST CASE | D8: TEST CATEGORY | E8: PRE-CONDITION | F8: TEST STEPS | G8: TEST DATA | H8: EXPECTED RESULTS | I8: POST CONDITION | J8: ACTUAL RESULT | K8: STATUS | L8: PRIORITY | M8: TESTER | N8: TEST DATE | O8: DEVICE | P8: BROWSER | Q8: ISSUE LINK | R8: COMMENT | S8: Run
A9: TC_001 | B9: Domestic Transfer | C9: A UnionPay China transfer is sent to a new receiver | D9: Positive | E9: User is on Domestic Transfer Page. | F9: -Given I log into the UMPay application with valid email credentials using "<row>" of "<excelSheetName>" of "<excelFileName>" -When I open the Domestic Transfer area -And I take the "UnionPay China" route from Domestic Transfer -Then the UnionPay amount form should be shown -When I enter the stated minimum as the UnionPay amount -Then the converted amount should be worked out -And the UnionPay transfer should be ready to continue -When I go on to the receiver step -And I send it to a new receiver in "<row>" of "<excelSheetName>" of "<excelFileName>", which moves real money -Then the transfer should go through | G9: Valid UMPay user | H9: User should be able to transfer to new entry | I9: User is still on Domestic Transfer page | J9: User can transfer to new entry | K9: PASS | L9: HIGH | M9: KIMA | O9: Window OS | P9: Edge | S9: Run
A10: TC_002 | B10: Domestic Transfer | C10: A UnionPay China transfer is sent to a saved receiver | D10: Positive | E10: User is on Domestic Transfer Page. | F10: -Given I log into the UMPay application with valid email credentials using "<row>" of "<excelSheetName>" of "<excelFileName>" -When I open the Domestic Transfer area -And I take the "UnionPay China" route from Domestic Transfer -Then the UnionPay amount form should be shown -When I enter the stated minimum as the UnionPay amount -Then the UnionPay transfer should be ready to continue -When I go on to the receiver step -And I send it to the saved receiver in "<row>" of "<excelSheetName>" of "<excelFileName>", which moves real money -Then the transfer should go through | G10: Valid UMPay user | H10: User should be able to transfer to saved receiver | I10: User is still on Domestic Transfer page | J10: User can transfer to saved receiver | K10: PASS | L10: HIGH | M10: KIMA | O10: Window OS | P10: Edge | S10: Run
A11: TC_003 | B11: Domestic Transfer | C11: UnionPay China will not go on with more than its stated maximum | D11: Negative | E11: User is on Domestic Transfer Page. | F11: -Given I log into the UMPay application with valid email credentials using "<row>" of "<excelSheetName>" of "<excelFileName>" -When I open the Domestic Transfer area -And I take the "UnionPay China" route from Domestic Transfer -Then the UnionPay amount form should be shown -When I enter one above the stated maximum as the UnionPay amount -Then the UnionPay transfer should not be ready to continue | G11: Valid UMPay user | H11: User should not be able to transfer | I11: User is still on Domestic Transfer page | J11: User can not transfer | K11: PASS | L11: HIGH | M11: KIMA | O11: Window OS | P11: Edge | S11: Run
A12: TC_004 | B12: Domestic Transfer | C12: UnionPay China will not go on with less than its stated minimum | D12: Negative | E12: User is on Domestic Transfer Page. | F12: -Given I log into the UMPay application with valid email credentials using "<row>" of "<excelSheetName>" of "<excelFileName>" -When I open the Domestic Transfer area -And I take the "UnionPay China" route from Domestic Transfer -Then the UnionPay amount form should be shown -When I enter one below the stated minimum as the UnionPay amount -Then the UnionPay transfer should not be ready to continue | G12: Valid UMPay user | H12: User should not be able to transfer | I12: User is still on Domestic Transfer page | J12: User can not transfer | K12: PASS | L12: HIGH | M12: KIMA | O12: Window OS | P12: Edge | S12: Run
A13: TC_005 | B13: Domestic Transfer | C13: Domestic Transfer offers exactly the China routes | D13: Positive | E13: User is signed in | F13: -Given I log into the UMPay application with valid email credentials using "<row>" of "<excelSheetName>" of "<excelFileName>" -When I open the Domestic Transfer area -Then the Domestic Transfer area should offer exactly its own routes | G13: Valid UMPay user | H13: The Domestic Transfer area should offer exactly its own China routes and nothing belonging to another area | I13: User is in the Domestic Transfer area | J13: The area offered exactly its own China routes | K13: PASS | L13: HIGH | M13: KIMA | N13: 46273 | O13: Window OS | P13: Chromium | S13: Run
A14: TC_006 | B14: Domestic Transfer | C14: A payment app route under maintenance refuses to open | D14: Negative | E14: User is in the Domestic Transfer area | F14: -Given I log into the UMPay application with valid email credentials using "<row>" of "<sheet>" of "<file>" -When I open the Domestic Transfer area -Then the Domestic Transfer route in "<row>" of "<sheet>" of "<file>" should be marked as under maintenance -When I take the route in "<row>" of "<sheet>" of "<file>" from Domestic Transfer -Then Domestic Transfer should refuse it with the message in "<row>" of "<sheet>" of "<file>" | G14: The two routes recorded as under maintenance | H14: A route marked under maintenance should say so and refuse to open with the message the platform gives, rather than opening a form that cannot be used | I14: User is in the Domestic Transfer area | J14: Both routes recorded as under maintenance were marked as such, and taking either was refused with the message the platform gives | K14: PASS | L14: MEDIUM | M14: KIMA | N14: 46273 | O14: Window OS | P14: Chromium | S14: Run
A15: TC_007 | B15: Domestic Transfer | C15: UnionPay China states its limits before anything is entered | D15: Positive | E15: User is on the UnionPay China form | F15: -Given I log into the UMPay application with valid email credentials using "<row>" of "<excelSheetName>" of "<excelFileName>" -When I open the Domestic Transfer area -And I take the "UnionPay China" route from Domestic Transfer -Then the UnionPay amount form should be shown -And the UnionPay form should state "Limit Min" -And the UnionPay form should state "Limit Max" -And the UnionPay transfer should not be ready to continue | G15: Valid UMPay user | H15: The form should state both Limit Min and Limit Max before anything is entered, and should not be ready to continue | I15: User is on the UnionPay China form | J15: The form stated both Limit Min and Limit Max before anything was entered, and was not ready to continue | K15: PASS | L15: MEDIUM | M15: KIMA | N15: 46273 | O15: Window OS | P15: Chromium | S15: Run
A16: TC_008 | B16: Domestic Transfer | C16: UnionPay China works out what the recipient receives | D16: Positive | E16: User is on the UnionPay China form | F16: -Given I log into the UMPay application with valid email credentials using "<row>" of "<excelSheetName>" of "<excelFileName>" -When I open the Domestic Transfer area -And I take the "UnionPay China" route from Domestic Transfer -Then the UnionPay amount form should be shown -And the UnionPay form should offer a converted amount -When I enter the stated minimum as the UnionPay amount -Then the converted amount should be worked out | G16: Amount: the stated minimum | H16: The form should work out and show what the recipient receives for the amount entered | I16: User is on the UnionPay China form | J16: Entering the stated minimum, the form worked the converted amount out to 68.96 | K16: PASS | L16: HIGH | M16: KIMA | N16: 46273 | O16: Window OS | P16: Chromium | S16: Run

Sheet Global_Transfer
A1: Project Name | B1: UMPay
A2: Module/Feature Name | B2: global Transfer | P2: HIGH | Q2: MEDIUM | R2: LOW
A3: Reference Document | N3: PASS | O3: =COUNTIF(K:K,"PASS") | P3: =COUNTIFS(K:K,"PASS",L:L,"HIGH") | Q3: =COUNTIFS(K:K,"PASS",L:L,"MEDIUM") | R3: =COUNTIFS(K:K,"PASS",L:L,"LOW")
A4: Created By | B4: KIMA | N4: FAIL | O4: =COUNTIF(K:K,"FAIL") | P4: =COUNTIFS(K:K,"FAIL",L:L,"HIGH") | Q4: =COUNTIFS(K:K,"FAIL",L:L,"MEDIUM") | R4: =COUNTIFS(K:K,"FAIL",L:L,"LOW")
A5: Date of Creation | B5: 46170 | N5: PENDING | O5: =COUNTIF(K:K,"PENDING") | P5: =COUNTIFS(K:K,"PENDING",L:L,"HIGH") | Q5: =COUNTIFS(K:K,"PENDING",L:L,"MEDIUM") | R5: =COUNTIFS(K:K,"PENDING",L:L,"LOW")
A6: Date of Review | B6: 46170
A8: TEST CASE ID | B8: TEST SCENARIO | C8: TEST CASE | D8: TEST CATEGORY | E8: PRE-CONDITION | F8: TEST STEPS | G8: TEST DATA | H8: EXPECTED RESULTS | I8: POST CONDITION | J8: ACTUAL RESULT | K8: STATUS | L8: PRIORITY | M8: TESTER | N8: TEST DATE | O8: DEVICE | P8: BROWSER | Q8: ISSUE LINK | R8: COMMENT | S8: Run
A9: TC_001 | B9: Global Transfer | C9: Successful Global Transfer for Outside China existing template | D9: Positive | E9: User is on Global Transfer Page. | F9: -Given I log into the UMPay application with valid email credentials using "<row>" of "<excelSheetName>" of "<excelFileName>" -When I navigate to Global Transfer page -Then I should be able to initiate a global transfer for existing template using "<row>" of "<excelSheetName>" of "<excelFileName>" | G9: Valid UMPay user | H9: User should be able to transfer to template | I9: User is still on Global Transfer page | J9: User can transfer to template | K9: PASS | L9: HIGH | M9: KIMA | O9: Window OS | P9: Edge | S9: Run
A10: TC_002 | B10: Global Transfer | C10: Successful Global Transfer for Outside China new Receiver | D10: Positive | E10: User is on Global Transfer Page. | F10: -Given I log into the UMPay application with valid email credentials using "<row>" of "<excelSheetName>" of "<excelFileName>" -When I navigate to Global Transfer page -Then I should be able to initiate a global transfer for new receiver account using "<row>" of "<excelSheetName>" of "<excelFileName>" | G10: Valid UMPay user | H10: User should be able to transfer to new receiver | I10: User is still on Global Transfer page | J10: User can transfer to new receiver | K10: PASS | L10: HIGH | M10: KIMA | O10: Window OS | P10: Edge | S10: Run
A11: TC_003 | B11: Global Transfer | C11: Successful Global Transfer for within China existing template | D11: Positive | E11: User is on Global Transfer Page. | F11: -Given I log into the UMPay application with valid email credentials using "<row>" of "<excelSheetName>" of "<excelFileName>" -When I navigate to Domestic Transfer page -Then I should be able to initiate a global transfer for existing template using "<row>" of "<excelSheetName>" of "<excelFileName>" | G11: Valid UMPay user | H11: User should be able to transfer to template | I11: User is still on Global Transfer page | J11: User can transfer to template | K11: PASS | L11: HIGH | M11: KIMA | O11: Window OS | P11: Edge | S11: Run
A12: TC_004 | B12: Global Transfer | C12: Successful Global Transfer for within China new Receiver | D12: Positive | E12: User is on Global Transfer Page. | F12: -Given I log into the UMPay application with valid email credentials using "<row>" of "<excelSheetName>" of "<excelFileName>" -When I navigate to Domestic Transfer page -Then I should be able to initiate a global transfer for new receiver account using "<row>" of "<excelSheetName>" of "<excelFileName>" | G12: Valid UMPay user | H12: User should be able to transfer to template | I12: User is still on Global Transfer page | J12: User can transfer to template | K12: PASS | L12: HIGH | M12: KIMA | O12: Window OS | P12: Edge | S12: Run
A13: TC_005 | B13: Global Transfer | C13: Global Transfer offers the transfer options outside China | D13: Positive | E13: User is signed in | F13: -Given I log into the UMPay application with valid email credentials using "<row>" of "<excelSheetName>" of "<excelFileName>" -When I open the Global Transfer area -Then the Global Transfer area should offer the route "UMPay Transfer to School Fees" -And the Global Transfer area should offer the route "UMPay Transfer to Personal Bank Account" -And the Global Transfer area should offer the route "UnionPay Global" -And the Global Transfer area should offer the route "UMPay Transfer to USDT" | G13: Valid UMPay user | H13: The Global Transfer area should offer the transfer options for outside China | I13: User is in the Global Transfer area | J13: The area offered the transfer options for outside China | K13: PASS | L13: HIGH | M13: KIMA | N13: 46273 | O13: Window OS | P13: Chromium | S13: Run
A14: TC_006 | B14: Global Transfer | C14: UnionPay Global offers the same form without a converted amount | D14: Positive | E14: User is in the Global Transfer area | F14: -Given I log into the UMPay application with valid email credentials using "<row>" of "<excelSheetName>" of "<excelFileName>" -When I open the Global Transfer area -And I take the "UnionPay Global" route from Global Transfer -Then the UnionPay amount form should be shown -And the UnionPay form should state "Limit Min" -And the UnionPay form should state "Limit Max" -And the UnionPay form should not offer a converted amount -And the UnionPay transfer should not be ready to continue | G14: Valid UMPay user | H14: UnionPay Global should offer the same form as its domestic counterpart, without the converted amount that only applies within China | I14: User is on the UnionPay Global form | J14: UnionPay Global offered the same form, with no converted amount on it | K14: PASS | L14: MEDIUM | M14: KIMA | N14: 46273 | O14: Window OS | P14: Chromium | S14: Run
A15: TC_007 | B15: Global Transfer | C15: A personal bank payout is sent | D15: Positive | E15: User is on the personal bank payout form | F15: -Given I log into the UMPay application with valid email credentials using "<row>" of "<excelSheetName>" of "<excelFileName>" -When I open the Global Transfer area -And I take the "UMPay Transfer to Personal Bank Account" route from Global Transfer -Then the "To Personal Bank Account" form should be shown -And the payout form should ask for a currency and an amount -And the payout form should state "Limit Min" -And the payout should not be ready to confirm -When I enter the stated minimum as the payout amount -And I choose the saved payout account in "<row>" of "<excelSheetName>" of "<excelFileName>" -And I confirm the payout, which moves real money -Then the payout should go through | G15: Valid UMPay user; a saved personal bank account | H15: A personal bank payout should be accepted and an order raised for it | I15: An order exists for the payout | J15: The payout was accepted and the platform raised order 1V5ZebQww5dr6XOz for it | K15: PASS | L15: HIGH | M15: KIMA | N15: 46273 | O15: Window OS | P15: Chromium | S15: Run
A16: TC_008 | B16: Global Transfer | C16: A USDT payout is sent | D16: Positive | E16: User is on the USDT payout form | F16: -Given I log into the UMPay application with valid email credentials using "<row>" of "<excelSheetName>" of "<excelFileName>" -When I open the Global Transfer area -And I take the "UMPay Transfer to USDT" route from Global Transfer -Then the "To USDT" form should be shown -And the payout form should ask for a currency and an amount -And the payout form should state "Limit Min" -And the payout should not be ready to confirm -When I enter the stated minimum as the payout amount -And I choose the saved payout account in "<row>" of "<excelSheetName>" of "<excelFileName>" -And I confirm the payout, which moves real money -Then the payout should go through | G16: Valid UMPay user; a USDT address | H16: A USDT payout should be accepted and an order raised for it | I16: An order exists for the payout | J16: The payout was accepted and the platform raised order Ld859bxvvnGrONgm for it | K16: PASS | L16: HIGH | M16: KIMA | N16: 46273 | O16: Window OS | P16: Chromium | S16: Run
A17: TC_009 | B17: Global Transfer | C17: A payout below the stated minimum cannot be confirmed | D17: Negative | E17: User is on a payout form | F17: -Given I log into the UMPay application with valid email credentials using "1" of "sheet1" of "GlobalTransfer_TestData.xlsx" -When I open the Global Transfer area -And I take the "<route>" route from Global Transfer -Then the "<form>" form should be shown -When I enter one below the stated minimum as the payout amount -Then the payout should not be ready to confirm | G17: Amount: one below the stated minimum | H17: A payout below the stated minimum should leave the form unable to confirm, on every route | I17: Nothing is sent | J17: On both routes - personal bank and USDT - one below the stated minimum left the payout not ready to confirm | K17: PASS | L17: HIGH | M17: KIMA | N17: 46273 | O17: Window OS | P17: Chromium | S17: Run
A18: TC_010 | B18: Global Transfer | C18: A payout of more than the wallet holds cannot be confirmed | D18: Negative | E18: User is on the USDT payout form | F18: -Given I log into the UMPay application with valid email credentials using "<row>" of "<excelSheetName>" of "<excelFileName>" -When I open the Global Transfer area -And I take the "UMPay Transfer to USDT" route from Global Transfer -Then the "To USDT" form should be shown -When I enter more than the wallet holds as the payout amount -Then the payout should not be ready to confirm | G18: Amount: more than the wallet holds | H18: A payout of more than the wallet holds should leave the form unable to confirm | I18: Nothing is sent | J18: More than the wallet holds left the payout not ready to confirm | K18: PASS | L18: HIGH | M18: KIMA | N18: 46273 | O18: Window OS | P18: Chromium | S18: Run

Sheet Profile
A1: Project Name | B1: UMPay
A2: Module/Feature Name | B2: Profile | P2: HIGH | Q2: MEDIUM | R2: LOW
A3: Reference Document | N3: PASS | O3: =COUNTIF(K:K,"PASS") | P3: =COUNTIFS(K:K,"PASS",L:L,"HIGH") | Q3: =COUNTIFS(K:K,"PASS",L:L,"MEDIUM") | R3: =COUNTIFS(K:K,"PASS",L:L,"LOW")
A4: Created By | B4: KIMA | N4: FAIL | O4: =COUNTIF(K:K,"FAIL") | P4: =COUNTIFS(K:K,"FAIL",L:L,"HIGH") | Q4: =COUNTIFS(K:K,"FAIL",L:L,"MEDIUM") | R4: =COUNTIFS(K:K,"FAIL",L:L,"LOW")
A5: Date of Creation | B5: 46170 | N5: PENDING | O5: =COUNTIF(K:K,"PENDING") | P5: =COUNTIFS(K:K,"PENDING",L:L,"HIGH") | Q5: =COUNTIFS(K:K,"PENDING",L:L,"MEDIUM") | R5: =COUNTIFS(K:K,"PENDING",L:L,"LOW")
A6: Date of Review | B6: 46170
A8: TEST CASE ID | B8: TEST SCENARIO | C8: TEST CASE | D8: TEST CATEGORY | E8: PRE-CONDITION | F8: TEST STEPS | G8: TEST DATA | H8: EXPECTED RESULTS | I8: POST CONDITION | J8: ACTUAL RESULT | K8: STATUS | L8: PRIORITY | M8: TESTER | N8: TEST DATE | O8: DEVICE | P8: BROWSER | Q8: ISSUE LINK | R8: COMMENT | S8: Run
A9: TC_001 | B9: Profile | C9: The drawer offers everything the account holder can reach | D9: Positive | E9: User is on Profile drawer | F9: -Given I log into the UMPay application with valid email credentials using "<row>" of "<excelSheetName>" of "<excelFileName>" -When I open the profile drawer -Then the profile drawer should offer "Trade Record, Referral Code, User List, Commission Listing, Fee Listing, Wallet, Payment, Template, Transfer Fee Setting, Document Verification, Security, Languages, Settings, Logout" | G9: Valid UMPay user | H9: User should be able to see all the options | I9: User is still on Profile drawer page | J9: User can see all the options | K9: PASS | L9: HIGH | M9: KIMA | O9: Window OS | P9: Edge | S9: Run
A10: TC_002 | B10: Profile | C10: The drawer displays details of account owner | D10: Positive | E10: User is on Profile drawer | F10: -Given I log into the UMPay application with valid email credentials using "<row>" of "<excelSheetName>" of "<excelFileName>" -When I open the profile drawer -Then the profile drawer should show the account details in "<row>" of "<excelSheetName>" of "<excelFileName>" | G10: Valid UMPay user | H10: User should be able to see details of account holder on Profile drawer | I10: User is still on Profile drawer page | J10: User can see details of account holder on Profile drawer | K10: PASS | L10: HIGH | M10: KIMA | O10: Window OS | P10: Edge | S10: Run
A11: TC_003 | B11: Profile | C11: Each function in the drawer opens its own page | D11: Positive | E11: User is on Profile drawer | F11: -Given I log into the UMPay application with valid email credentials using "<row>" of "<excelSheetName>" of "<excelFileName>" -When I open the profile drawer -And I open "<function>" from the profile drawer -Then it should open the "<heading>" page at "<address>" | G11: Valid UMPay user | H11: User should be able to open each option | I11: User is still on Profile drawer page | J11: User can open each option | K11: PASS | L11: HIGH | M11: KIMA | O11: Window OS | P11: Edge | S11: Run
A12: TC_004 | B12: Profile | C12: Logging out signs the account out | D12: Positive | E12: User is on Profile drawer | F12: -Given I log into the UMPay application with valid email credentials using "<row>" of "<excelSheetName>" of "<excelFileName>" -When I open the profile drawer -And I ask to log out -Then the application should ask whether I mean it -When I answer "Yes" -Then I should be signed out | G12: Valid UMPay user | H12: User should be able to logout | I12: User is still on Profile drawer page | J12: User can logout | K12: PASS | L12: HIGH | M12: KIMA | O12: Window OS | P12: Edge | S12: Run
A13: TC_005 | B13: Profile | C13: Copying the referral code puts it on the clipboard | D13: Positive | E13: User is signed in and the profile drawer is open | F13: -Given I log into the UMPay application with valid email credentials using "<row>" of "<excelSheetName>" of "<excelFileName>" -When I open the profile drawer -And I copy my referral code -Then the referral code should be on the clipboard | G13: Valid UMPay user | H13: The control beside the referral code should copy it, and what reaches the clipboard should be the code the drawer shows rather than anything else | I13: The referral code is on the clipboard | J13: The drawer showed 3RNAYW and offered a control beside it. Pressing it put 3RNAYW on the clipboard - the same code the drawer shows | K13: PASS | L13: HIGH | M13: KIMA | N13: 46273 | O13: Window OS | P13: Chromium | S13: Run
A14: TC_006 | B14: Profile | C14: The application confirms the referral code was copied | D14: Positive | E14: User is signed in and the profile drawer is open | F14: -Given I log into the UMPay application with valid email credentials using "<row>" of "<excelSheetName>" of "<excelFileName>" -When I open the profile drawer -And I copy my referral code -Then the application should confirm the referral code was copied | G14: Valid UMPay user | H14: The application should say the code was copied and name it, since copying leaves nothing on the screen to see and there would otherwise be no way to tell the press was heard | I14: The referral code is on the clipboard | J14: The application answered "Referral code 3RNAYW", naming the code it had copied | K14: PASS | L14: MEDIUM | M14: KIMA | N14: 46273 | O14: Window OS | P14: Chromium | S14: Run
A15: TC_007 | B15: Profile | C15: The referral code does not change between readings | D15: Positive | E15: User is signed in | F15: -Given I log into the UMPay application with valid email credentials using "<row>" of "<excelSheetName>" of "<excelFileName>" -When I open the profile drawer -Then the referral code should read the same each time the drawer is opened | G15: Valid UMPay user | H15: The code should read the same each time the drawer is opened, since a code that changed would break every link and message this account had already sent out | I15: User is on the Home page | J15: The code read 3RNAYW on both openings of the drawer | K15: PASS | L15: HIGH | M15: KIMA | N15: 46273 | O15: Window OS | P15: Chromium | S15: Run

Sheet Bills
A1: Project Name | B1: UMPay
A2: Module/Feature Name | B2: Bills | P2: HIGH | Q2: MEDIUM | R2: LOW
A3: Reference Document | N3: PASS | O3: =COUNTIF(K:K,"PASS") | P3: =COUNTIFS(K:K,"PASS",L:L,"HIGH") | Q3: =COUNTIFS(K:K,"PASS",L:L,"MEDIUM") | R3: =COUNTIFS(K:K,"PASS",L:L,"LOW")
A4: Created By | B4: KIMA | N4: FAIL | O4: =COUNTIF(K:K,"FAIL") | P4: =COUNTIFS(K:K,"FAIL",L:L,"HIGH") | Q4: =COUNTIFS(K:K,"FAIL",L:L,"MEDIUM") | R4: =COUNTIFS(K:K,"FAIL",L:L,"LOW")
A5: Date of Creation | B5: 46272 | N5: PENDING | O5: =COUNTIF(K:K,"PENDING") | P5: =COUNTIFS(K:K,"PENDING",L:L,"HIGH") | Q5: =COUNTIFS(K:K,"PENDING",L:L,"MEDIUM") | R5: =COUNTIFS(K:K,"PENDING",L:L,"LOW")
A6: Date of Review | B6: 46272
A8: TEST CASE ID | B8: TEST SCENARIO | C8: TEST CASE | D8: TEST CATEGORY | E8: PRE-CONDITION | F8: TEST STEPS | G8: TEST DATA | H8: EXPECTED RESULTS | I8: POST CONDITION | J8: ACTUAL RESULT | K8: STATUS | L8: PRIORITY | M8: TESTER | N8: TEST DATE | O8: DEVICE | P8: BROWSER | Q8: ISSUE LINK | R8: COMMENT | S8: Run
A9: TC_001 | B9: Bills | C9: The Bills page lists the account's transactions | D9: Positive | E9: User is signed in | F9: -Given I log into the UMPay application with valid email credentials using "<row>" of "<excelSheetName>" of "<excelFileName>" -When I open the Bills page -Then the ledger should list the account's transactions | G9: Valid UMPay user | H9: Every transaction the account has made should be listed, newest first, each naming its kind, when it happened and how much moved | I9: User is on the Bills page | J9: The ledger listed the account's transactions, newest first | K9: PASS | L9: HIGH | M9: KIMA | N9: 46272 | O9: Window OS | P9: Chromium | S9: Run
A10: TC_002 | B10: Bills | C10: The ledger can be narrowed to any kind of transaction | D10: Positive | E10: User is on the Bills page | F10: -Given I log into the UMPay application with valid email credentials using "<row>" of "<excelSheetName>" of "<excelFileName>" -When I open the Bills page -Then the ledger should offer to filter by "All, Transfer, Convert, Deposit, Withdraw, Transfer To Card, Card Withdraw, Alipay Transfer, Direct Deposit, Direct Withdraw, Unionpay Transfer, Voucher Fee, International School Fee, Pay, UnionPay Card Topup" | G10: Valid UMPay user | H10: The filter should offer every kind of transaction the platform records | I10: User is on the Bills page | J10: The type filter offered every kind the platform records | K10: PASS | L10: MEDIUM | M10: KIMA | N10: 46272 | O10: Window OS | P10: Chromium | S10: Run
A11: TC_003 | B11: Bills Filter | C11: Filtering by a kind of transaction leaves only that kind | D11: Positive | E11: User is on the Bills page | F11: -Given I log into the UMPay application with valid email credentials using "<row>" of "<excelSheetName>" of "<excelFileName>" -When I open the Bills page -And I filter the ledger by the type in "<row>" of "<excelSheetName>" of "<excelFileName>" -Then every transaction listed should be a "Convert" | G11: Type: Convert | H11: Only transactions of the chosen kind should be listed | I11: User is on the Bills page | J11: Filtering by Convert left only Convert transactions | K11: PASS | L11: HIGH | M11: KIMA | N11: 46272 | O11: Window OS | P11: Chromium | S11: Run
A12: TC_004 | B12: Bills Filter | C12: Filtering by amount leaves only what falls inside the band | D12: Positive | E12: User is on the Bills page | F12: -Given I log into the UMPay application with valid email credentials using "<row>" of "<excelSheetName>" of "<excelFileName>" -When I open the Bills page -And I filter the ledger by the amounts in "<row>" of "<excelSheetName>" of "<excelFileName>" -Then every amount listed should be between "1" and "100" | G12: Amount between 1 and 100 | H12: Only transactions whose amount falls inside the band should be listed | I12: User is on the Bills page | J12: Only amounts between 1 and 100 were listed | K12: PASS | L12: MEDIUM | M12: KIMA | N12: 46272 | O12: Window OS | P12: Chromium | S12: Run
A13: TC_005 | B13: Bills Filter | C13: Filtering by day leaves only that day | D13: Positive | E13: User is on the Bills page | F13: -Given I log into the UMPay application with valid email credentials using "<row>" of "<excelSheetName>" of "<excelFileName>" -When I open the Bills page -And I filter the ledger to the day of its newest transaction -Then every transaction listed should be from that day | G13: The day the newest transaction happened | H13: Only transactions from that day should be listed | I13: User is on the Bills page | J13: Only transactions from the chosen day were listed | K13: PASS | L13: MEDIUM | M13: KIMA | N13: 46272 | O13: Window OS | P13: Chromium | S13: Run
A14: TC_006 | B14: Bills Filter | C14: A stretch of days with nothing in it says so | D14: Negative | E14: User is on the Bills page | F14: -Given I log into the UMPay application with valid email credentials using "<row>" of "<excelSheetName>" of "<excelFileName>" -When I open the Bills page -And I filter the ledger by the dates in "<row>" of "<excelSheetName>" of "<excelFileName>" -Then the ledger should say it has nothing to show | G14: Dates: 2020-01-01 to 2020-01-02 | H14: The page should say it has no data rather than showing an unfiltered list | I14: User is on the Bills page | J14: The ledger said it had no data for those dates | K14: PASS | L14: MEDIUM | M14: KIMA | N14: 46272 | O14: Window OS | P14: Chromium | S14: Run
A15: TC_007 | B15: Bills Filter | C15: Reset brings the whole ledger back | D15: Positive | E15: A filter matching nothing has been applied | F15: -Given I log into the UMPay application with valid email credentials using "<row>" of "<excelSheetName>" of "<excelFileName>" -When I open the Bills page -And I filter the ledger by the dates in "<row>" of "<excelSheetName>" of "<excelFileName>" -Then the ledger should say it has nothing to show -When I reset the filters -Then the ledger should list the account's transactions again | G15: Dates: 2020-01-01 to 2020-01-02 | H15: Reset should clear the filter and list the account transactions again | I15: User is on the Bills page | J15: Reset cleared the filter and brought the whole ledger back | K15: PASS | L15: HIGH | M15: KIMA | N15: 46272 | O15: Window OS | P15: Chromium | S15: Run
A16: TC_008 | B16: Bills Detail | C16: A transaction opens its own detail | D16: Positive | E16: User is on the Bills page | F16: -Given I log into the UMPay application with valid email credentials using "<row>" of "<excelSheetName>" of "<excelFileName>" -When I open the Bills page -And I open the newest transaction -Then the transaction detail should name the transaction, when it happened and what moved | G16: Valid UMPay user | H16: The transaction should open a detail naming its number, when it happened and what moved | I16: User is on the Bills page | J16: The detail named the transaction number, the date and what moved | K16: PASS | L16: HIGH | M16: KIMA | N16: 46272 | O16: Window OS | P16: Chromium | S16: Run
A17: TC_009 | B17: Bills Detail | C17: A transaction's receipt can be downloaded | D17: Positive | E17: A transaction detail is open | F17: -Given I log into the UMPay application with valid email credentials using "<row>" of "<excelSheetName>" of "<excelFileName>" -When I open the Bills page -And I open the newest transaction -Then downloading the transaction should produce a file | G17: Valid UMPay user | H17: Download should produce a receipt file with content in it | I17: User is on the Bills page | J17: Download produced a receipt file with content in it | K17: PASS | L17: MEDIUM | M17: KIMA | N17: 46272 | O17: Window OS | P17: Chromium | S17: Run
A18: TC_010 | B18: Bills Detail | C18: A transaction can be shared | D18: Positive | E18: A transaction detail is open | F18: -Given I log into the UMPay application with valid email credentials using "<row>" of "<excelSheetName>" of "<excelFileName>" -When I open the Bills page -And I open the newest transaction -When I share the transaction -Then the sharing choices should offer a way to copy the transaction | G18: Valid UMPay user | H18: Share should offer a way to copy the transaction | I18: User is on the Bills page | J18: Share offered a way to copy the transaction | K18: PASS | L18: MEDIUM | M18: KIMA | N18: 46272 | O18: Window OS | P18: Chromium | S18: Run

Sheet Notification
A1: Project Name | B1: UMPay
A2: Module/Feature Name | B2: Notification | P2: HIGH | Q2: MEDIUM | R2: LOW
A3: Reference Document | N3: PASS | O3: =COUNTIF(K:K,"PASS") | P3: =COUNTIFS(K:K,"PASS",L:L,"HIGH") | Q3: =COUNTIFS(K:K,"PASS",L:L,"MEDIUM") | R3: =COUNTIFS(K:K,"PASS",L:L,"LOW")
A4: Created By | B4: KIMA | N4: FAIL | O4: =COUNTIF(K:K,"FAIL") | P4: =COUNTIFS(K:K,"FAIL",L:L,"HIGH") | Q4: =COUNTIFS(K:K,"FAIL",L:L,"MEDIUM") | R4: =COUNTIFS(K:K,"FAIL",L:L,"LOW")
A5: Date of Creation | B5: 46272 | N5: PENDING | O5: =COUNTIF(K:K,"PENDING") | P5: =COUNTIFS(K:K,"PENDING",L:L,"HIGH") | Q5: =COUNTIFS(K:K,"PENDING",L:L,"MEDIUM") | R5: =COUNTIFS(K:K,"PENDING",L:L,"LOW")
A6: Date of Review | B6: 46272
A8: TEST CASE ID | B8: TEST SCENARIO | C8: TEST CASE | D8: TEST CATEGORY | E8: PRE-CONDITION | F8: TEST STEPS | G8: TEST DATA | H8: EXPECTED RESULTS | I8: POST CONDITION | J8: ACTUAL RESULT | K8: STATUS | L8: PRIORITY | M8: TESTER | N8: TEST DATE | O8: DEVICE | P8: BROWSER | Q8: ISSUE LINK | R8: COMMENT | S8: Run
A9: TC_001 | B9: Notification | C9: The bell opens the account's notifications | D9: Positive | E9: User is signed in | F9: -Given I log into the UMPay application with valid email credentials using "<row>" of "<excelSheetName>" of "<excelFileName>" -When I open the Notifications page -Then the notifications should list what the platform has told the account | G9: Valid UMPay user | H9: The bell should open the notification page, listing what the platform has told the account | I9: User is on the Notification page | J9: The bell opened /v2/notification and listed the notifications | K9: PASS | L9: HIGH | M9: KIMA | N9: 46272 | O9: Window OS | P9: Chromium | S9: Run
A10: TC_002 | B10: Notification | C10: The notifications are kept in three tabs | D10: Positive | E10: User is on the Notification page | F10: -Given I log into the UMPay application with valid email credentials using "<row>" of "<excelSheetName>" of "<excelFileName>" -When I open the Notifications page -Then the notifications should offer the tabs "Transactions, Announcements, Messages" | G10: Valid UMPay user | H10: The page should offer the Transactions, Announcements and Messages tabs | I10: User is on the Notification page | J10: Transactions, Announcements and Messages were all offered | K10: PASS | L10: HIGH | M10: KIMA | N10: 46272 | O10: Window OS | P10: Chromium | S10: Run
A11: TC_003 | B11: Notification Transactions | C11: Every transaction notification names its kind, amount, currency and date | D11: Positive | E11: User is on the Notification page | F11: -Given I log into the UMPay application with valid email credentials using "<row>" of "<excelSheetName>" of "<excelFileName>" -When I open the Notifications page -Then each notification should name its kind, amount, currency and when it happened | G11: Valid UMPay user | H11: Every card should name the kind of transaction, the amount, the currency and when it happened | I11: User is on the Notification page | J11: Every card named its kind, amount, currency and created date | K11: PASS | L11: HIGH | M11: KIMA | N11: 46272 | O11: Window OS | P11: Chromium | S11: Run
A12: TC_004 | B12: Notification Transactions | C12: The transaction notifications are listed newest first | D12: Positive | E12: User is on the Notification page | F12: -Given I log into the UMPay application with valid email credentials using "<row>" of "<excelSheetName>" of "<excelFileName>" -When I open the Notifications page -Then the notifications should be listed newest first | G12: Valid UMPay user | H12: The newest notification should be at the top and the oldest at the bottom | I12: User is on the Notification page | J12: The notifications were listed newest first | K12: PASS | L12: HIGH | M12: KIMA | N12: 46272 | O12: Window OS | P12: Chromium | S12: Run
A13: TC_005 | B13: Notification Transactions | C13: Each amount is written with the symbol its currency uses | D13: Positive | E13: User is on the Notification page | F13: -Given I log into the UMPay application with valid email credentials using "<row>" of "<excelSheetName>" of "<excelFileName>" -When I open the Notifications page -Then each amount should be written with the symbol its currency uses | G13: Valid UMPay user | H13: Each amount should be a figure carrying its wallet symbol, and a wallet should be written the same way on every card | I13: User is on the Notification page | J13: Each amount carried its wallet symbol, the same one throughout | K13: PASS | L13: MEDIUM | M13: KIMA | N13: 46272 | O13: Window OS | P13: Chromium | S13: Run
A14: TC_006 | B14: Notification Transactions | C14: Reaching the end of the list brings in older notifications | D14: Positive | E14: User is on the Notification page | F14: -Given I log into the UMPay application with valid email credentials using "<row>" of "<excelSheetName>" of "<excelFileName>" -When I open the Notifications page -And I scroll to the end of the notifications -Then more notifications should have been brought in | G14: Valid UMPay user | H14: Scrolling to the bottom should bring in the next of the notifications | I14: User is on the Notification page | J14: Reaching the end took the list from 20 notifications to 60 | K14: PASS | L14: HIGH | M14: KIMA | N14: 46272 | O14: Window OS | P14: Chromium | S14: Run
A15: TC_007 | B15: Notification Announcements | C15: The Announcements tab shows what the platform has announced | D15: Positive | E15: User is on the Notification page | F15: -Given I log into the UMPay application with valid email credentials using "<row>" of "<excelSheetName>" of "<excelFileName>" -When I open the Notifications page -And I move to the tab named in "<row>" of "<excelSheetName>" of "<excelFileName>" -Then every announcement should carry a message and when it arrived | G15: Tab: Announcements | H15: Every announcement should carry its own message and when it arrived | I15: User is on the Notification page | J15: All 20 announcements carried a message and when they arrived | K15: PASS | L15: HIGH | M15: KIMA | N15: 46272 | O15: Window OS | P15: Chromium | S15: Run
A16: TC_008 | B16: Notification Messages | C16: The Messages tab shows the conversation with customer service | D16: Positive | E16: User is on the Notification page | F16: -Given I log into the UMPay application with valid email credentials using "<row>" of "<excelSheetName>" of "<excelFileName>" -When I open the Notifications page -And I move to the tab named in "<row>" of "<excelSheetName>" of "<excelFileName>" -Then the conversation with customer service should be shown | G16: Tab: Messages | H16: The conversation with customer service should be shown | I16: User is on the Notification page | J16: The conversation with customer service was shown | K16: PASS | L16: MEDIUM | M16: KIMA | N16: 46272 | O16: Window OS | P16: Chromium | S16: Run
A17: TC_009 | B17: Notification Tabs | C17: Moving to another tab changes what is listed | D17: Positive | E17: User is on the Notification page | F17: -Given I log into the UMPay application with valid email credentials using "<row>" of "<excelSheetName>" of "<excelFileName>" -When I open the Notifications page -And I move to the tab named in "<row>" of "<excelSheetName>" of "<excelFileName>" -Then what is listed should change | G17: Tab: Announcements | H17: Choosing another tab should change what is listed rather than only highlighting the tab | I17: User is on the Notification page | J17: Choosing another tab changed what was listed | K17: PASS | L17: HIGH | M17: KIMA | N17: 46272 | O17: Window OS | P17: Chromium | S17: Run
A18: TC_010 | B18: Notification Read State | C18: The unread count agrees with what the list marks unread | D18: Positive | E18: User is on the Notification page | F18: -Given I log into the UMPay application with valid email credentials using "<row>" of "<excelSheetName>" of "<excelFileName>" -When I open the Notifications page -And I look through the notifications -Then the unread count should agree with the marks in the list | G18: Valid UMPay user | H18: The list should never mark more notifications unread than the bell says are waiting, and nothing should be marked when the bell says nothing is unread | I18: The notifications seen are marked read | J18: The list marked 116 unread against a bell of 412, which agree | K18: PASS | L18: HIGH | M18: KIMA | N18: 46272 | O18: Window OS | P18: Chromium | S18: Run
A19: TC_011 | B19: Notification Read State | C19: What has been read is not forgotten when the page is loaded again | D19: Positive | E19: The notifications have been looked through | F19: -Given I log into the UMPay application with valid email credentials using "<row>" of "<excelSheetName>" of "<excelFileName>" -When I open the Notifications page -And I look through the notifications -Then looking should not have added to the unread count -When I reload the notifications -Then what has been seen should still be marked read | G19: Valid UMPay user | H19: Looking should never add to the unread count, and the count should not climb back after the page is loaded again | I19: The notifications seen are marked read | J19: The count did not climb after looking, nor after a reload | K19: PASS | L19: HIGH | M19: KIMA | N19: 46272 | O19: Window OS | P19: Chromium | S19: Run

Sheet Trade_Record
A1: Project Name | B1: UMPay
A2: Module/Feature Name | B2: Trade Record | P2: HIGH | Q2: MEDIUM | R2: LOW
A3: Reference Document | N3: PASS | O3: =COUNTIF(K:K,"PASS") | P3: =COUNTIFS(K:K,"PASS",L:L,"HIGH") | Q3: =COUNTIFS(K:K,"PASS",L:L,"MEDIUM") | R3: =COUNTIFS(K:K,"PASS",L:L,"LOW")
A4: Created By | B4: KIMA | N4: FAIL | O4: =COUNTIF(K:K,"FAIL") | P4: =COUNTIFS(K:K,"FAIL",L:L,"HIGH") | Q4: =COUNTIFS(K:K,"FAIL",L:L,"MEDIUM") | R4: =COUNTIFS(K:K,"FAIL",L:L,"LOW")
A5: Date of Creation | B5: 46272 | N5: PENDING | O5: =COUNTIF(K:K,"PENDING") | P5: =COUNTIFS(K:K,"PENDING",L:L,"HIGH") | Q5: =COUNTIFS(K:K,"PENDING",L:L,"MEDIUM") | R5: =COUNTIFS(K:K,"PENDING",L:L,"LOW")
A6: Date of Review | B6: 46272
A8: TEST CASE ID | B8: TEST SCENARIO | C8: TEST CASE | D8: TEST CATEGORY | E8: PRE-CONDITION | F8: TEST STEPS | G8: TEST DATA | H8: EXPECTED RESULTS | I8: POST CONDITION | J8: ACTUAL RESULT | K8: STATUS | L8: PRIORITY | M8: TESTER | N8: TEST DATE | O8: DEVICE | P8: BROWSER | Q8: ISSUE LINK | R8: COMMENT | S8: Run
A9: TC_001 | B9: Trade Record | C9: The profile drawer opens the account's trade record | D9: Positive | E9: User is signed in | F9: -Given I log into the UMPay application with valid email credentials using "<row>" of "<excelSheetName>" of "<excelFileName>" -When I open the Trade Record page -Then the trade record should list the orders the account has raised | G9: Valid UMPay user | H9: The trade record should open from the profile drawer, listing the orders the account has raised | I9: User is on the Trade Record page | J9: The drawer opened /v2/trade-record and listed 20 orders | K9: PASS | L9: HIGH | M9: KIMA | N9: 46272 | O9: Window OS | P9: Chromium | S9: Run
A10: TC_002 | B10: Trade Record | C10: The trade record is kept in three tabs | D10: Positive | E10: User is on the Trade Record page | F10: -Given I log into the UMPay application with valid email credentials using "<row>" of "<excelSheetName>" of "<excelFileName>" -When I open the Trade Record page -Then the trade record should offer the tabs "Deposit/Withdraw, International Transfer, International School Fee" | G10: Valid UMPay user | H10: The page should offer the Deposit/Withdraw, International Transfer and International School Fee tabs | I10: User is on the Trade Record page | J10: Deposit/Withdraw, International Transfer and International School Fee were all offered | K10: PASS | L10: HIGH | M10: KIMA | N10: 46272 | O10: Window OS | P10: Chromium | S10: Run
A11: TC_003 | B11: Trade Record Deposit/Withdraw | C11: Every order names its number, currency, amount and how it ended | D11: Positive | E11: User is on the Trade Record page | F11: -Given I log into the UMPay application with valid email credentials using "<row>" of "<excelSheetName>" of "<excelFileName>" -When I open the Trade Record page -Then every order should name its number, currency, amount and how it ended | G11: Valid UMPay user | H11: Every order should name its number, its currency, its amount and the status it ended in | I11: User is on the Trade Record page | J11: All 20 orders named their number, currency, amount and status | K11: PASS | L11: HIGH | M11: KIMA | N11: 46272 | O11: Window OS | P11: Chromium | S11: Run
A12: TC_004 | B12: Trade Record Deposit/Withdraw | C12: No two orders share a number | D12: Positive | E12: User is on the Trade Record page | F12: -Given I log into the UMPay application with valid email credentials using "<row>" of "<excelSheetName>" of "<excelFileName>" -When I open the Trade Record page -Then no two orders should share a number | G12: Valid UMPay user | H12: No order number should appear more than once in the list | I12: User is on the Trade Record page | J12: All 20 orders carried a number of their own | K12: PASS | L12: HIGH | M12: KIMA | N12: 46272 | O12: Window OS | P12: Chromium | S12: Run
A13: TC_005 | B13: Trade Record Deposit/Withdraw | C13: A converted order shows both what was received and the rate | D13: Positive | E13: User is on the Trade Record page | F13: -Given I log into the UMPay application with valid email credentials using "<row>" of "<excelSheetName>" of "<excelFileName>" -When I open the Trade Record page -Then any converted order should show both what was received and the rate | G13: Valid UMPay user | H13: An order that was converted should show both the amount received and the exchange rate, never one without the other | I13: User is on the Trade Record page | J13: 6 of the 20 orders were converted, each showing both the received amount and the rate | K13: PASS | L13: MEDIUM | M13: KIMA | N13: 46272 | O13: Window OS | P13: Chromium | S13: Run
A14: TC_006 | B14: Trade Record Deposit/Withdraw | C14: Reaching the end of the record brings in older orders | D14: Positive | E14: User is on the Trade Record page | F14: -Given I log into the UMPay application with valid email credentials using "<row>" of "<excelSheetName>" of "<excelFileName>" -When I open the Trade Record page -And I scroll to the end of the trade record -Then more orders should have been brought in | G14: Valid UMPay user | H14: Scrolling to the bottom should bring in the next of the orders | I14: User is on the Trade Record page | J14: Reaching the end took the list from 20 orders to 60 | K14: PASS | L14: HIGH | M14: KIMA | N14: 46272 | O14: Window OS | P14: Chromium | S14: Run
A15: TC_007 | B15: Trade Record Transfers | C15: An international transfer is charged its fee plus its amount | D15: Positive | E15: User is on the Trade Record page | F15: -Given I log into the UMPay application with valid email credentials using "<row>" of "<excelSheetName>" of "<excelFileName>" -When I open the Trade Record page -And I move to the trade record tab named in "<row>" of "<excelSheetName>" of "<excelFileName>" -Then every international transfer should add up to its total | G15: Tab: International Transfer | H15: The total charged should be exactly the fee plus the amount sent | I15: User is on the Trade Record page | J15: All 20 international transfers were charged exactly their fee plus their amount | K15: PASS | L15: HIGH | M15: KIMA | N15: 46272 | O15: Window OS | P15: Chromium | S15: Run
A16: TC_008 | B16: Trade Record Transfers | C16: A school fee order names its order number, total and when it was created | D16: Positive | E16: User is on the Trade Record page | F16: -Given I log into the UMPay application with valid email credentials using "<row>" of "<excelSheetName>" of "<excelFileName>" -When I open the Trade Record page -And I move to the trade record tab named in "<row>" of "<excelSheetName>" of "<excelFileName>" -Then every school fee order should name its order number, total and when it was created | G16: Tab: International School Fee | H16: Every school fee order should name its order number, its total and when it was created | I16: User is on the Trade Record page | J16: Every school fee order named its order number, total and created date | K16: PASS | L16: MEDIUM | M16: KIMA | N16: 46272 | O16: Window OS | P16: Chromium | S16: Run
A17: TC_009 | B17: Trade Record | C17: Moving to another tab changes what the record lists | D17: Positive | E17: User is on the Trade Record page | F17: -Given I log into the UMPay application with valid email credentials using "<row>" of "<excelSheetName>" of "<excelFileName>" -When I open the Trade Record page -And I move to the trade record tab named in "<row>" of "<excelSheetName>" of "<excelFileName>" -Then what the trade record lists should change | G17: Tab: International Transfer | H17: Choosing another tab should change what is listed rather than only highlighting the tab | I17: User is on the Trade Record page | J17: Choosing another tab changed what was listed | K17: PASS | L17: HIGH | M17: KIMA | N17: 46272 | O17: Window OS | P17: Chromium | S17: Run
A18: TC_010 | B18: Trade Record Order | C18: An order in the record opens the order itself | D18: Positive | E18: User is on the Trade Record page | F18: -Given I log into the UMPay application with valid email credentials using "<row>" of "<excelSheetName>" of "<excelFileName>" -When I open the Trade Record page -And I open the newest order -Then the order's own page should open | G18: Valid UMPay user | H18: Opening an order should go to that order's own page, at an address naming the order | I18: User is on the order's own page | J18: The order opened at /deposit/zG0XAW5778xqoDYL?orderId=zG0XAW5778xqoDYL&orderStatus=6&navigateFrom=%2Fv2%2Ftrade-record | K18: PASS | L18: HIGH | M18: KIMA | N18: 46272 | O18: Window OS | P18: Chromium | S18: Run
A19: TC_011 | B19: Trade Record Order | C19: Going back from an order returns to the trade record | D19: Positive | E19: User is on an order's own page | F19: -Given I log into the UMPay application with valid email credentials using "<row>" of "<excelSheetName>" of "<excelFileName>" -When I open the Trade Record page -And I open the newest order -Then the order's own page should open -When I go back to the trade record -Then the trade record should be listing again | G19: Valid UMPay user | H19: Going back should return to the trade record, still listing the orders | I19: User is on the Trade Record page | J19: Going back returned to the trade record, still listing its orders | K19: PASS | L19: HIGH | M19: KIMA | N19: 46272 | O19: Window OS | P19: Chromium | S19: Run

Sheet Wallet
A1: Project Name | B1: UMPay
A2: Module/Feature Name | B2: Wallet | P2: HIGH | Q2: MEDIUM | R2: LOW
A3: Reference Document | N3: PASS | O3: =COUNTIF(K:K,"PASS") | P3: =COUNTIFS(K:K,"PASS",L:L,"HIGH") | Q3: =COUNTIFS(K:K,"PASS",L:L,"MEDIUM") | R3: =COUNTIFS(K:K,"PASS",L:L,"LOW")
A4: Created By | B4: KIMA | N4: FAIL | O4: =COUNTIF(K:K,"FAIL") | P4: =COUNTIFS(K:K,"FAIL",L:L,"HIGH") | Q4: =COUNTIFS(K:K,"FAIL",L:L,"MEDIUM") | R4: =COUNTIFS(K:K,"FAIL",L:L,"LOW")
A5: Date of Creation | B5: 46272 | N5: PENDING | O5: =COUNTIF(K:K,"PENDING") | P5: =COUNTIFS(K:K,"PENDING",L:L,"HIGH") | Q5: =COUNTIFS(K:K,"PENDING",L:L,"MEDIUM") | R5: =COUNTIFS(K:K,"PENDING",L:L,"LOW")
A6: Date of Review | B6: 46272
A8: TEST CASE ID | B8: TEST SCENARIO | C8: TEST CASE | D8: TEST CATEGORY | E8: PRE-CONDITION | F8: TEST STEPS | G8: TEST DATA | H8: EXPECTED RESULTS | I8: POST CONDITION | J8: ACTUAL RESULT | K8: STATUS | L8: PRIORITY | M8: TESTER | N8: TEST DATE | O8: DEVICE | P8: BROWSER | Q8: ISSUE LINK | R8: COMMENT | S8: Run
A9: TC_001 | B9: Wallet | C9: The profile drawer opens the account's wallets | D9: Positive | E9: User is signed in | F9: -Given I log into the UMPay application with valid email credentials using "<row>" of "<excelSheetName>" of "<excelFileName>" -When I open the Wallet page -Then the page should list the wallets the account holds | G9: Valid UMPay user | H9: The wallet page should open from the profile drawer, listing every wallet the account holds | I9: User is on the Wallet page | J9: The drawer opened /v2/wallet, listing 10 wallets: HKD, IDR, VND, PHP, MYR, BDT, USD, THB, MXN, BRL | K9: PASS | L9: HIGH | M9: KIMA | N9: 46272 | O9: Window OS | P9: Chromium | S9: Run
A10: TC_002 | B10: Wallet List | C10: Every wallet names its currency, country, balance and what is blocked | D10: Positive | E10: User is on the Wallet page | F10: -Given I log into the UMPay application with valid email credentials using "<row>" of "<excelSheetName>" of "<excelFileName>" -When I open the Wallet page -Then every wallet should name its currency, country, balance and what is blocked | G10: Valid UMPay user | H10: Every wallet should name its currency, its country, its balance and its blocked amount | I10: User is on the Wallet page | J10: All 10 wallets named their currency, country, balance and blocked amount | K10: PASS | L10: HIGH | M10: KIMA | N10: 46272 | O10: Window OS | P10: Chromium | S10: Run
A11: TC_003 | B11: Wallet List | C11: Exactly one wallet is the main wallet | D11: Positive | E11: User is on the Wallet page | F11: -Given I log into the UMPay application with valid email credentials using "<row>" of "<excelSheetName>" of "<excelFileName>" -When I open the Wallet page -Then exactly one wallet should be the main wallet | G11: Valid UMPay user | H11: One wallet should be marked as the main wallet, and every other should offer to become it | I11: User is on the Wallet page | J11: The main wallet was HKD, and the other 9 each offered to become it | K11: PASS | L11: HIGH | M11: KIMA | N11: 46272 | O11: Window OS | P11: Chromium | S11: Run
A12: TC_004 | B12: Wallet List | C12: Each wallet states its balance and what is blocked in its own currency | D12: Positive | E12: User is on the Wallet page | F12: -Given I log into the UMPay application with valid email credentials using "<row>" of "<excelSheetName>" of "<excelFileName>" -When I open the Wallet page -Then each wallet's figures should be written in its own currency | G12: Valid UMPay user | H12: A wallet's balance and its blocked amount should be written in the same currency symbol | I12: User is on the Wallet page | J12: Every wallet used one symbol throughout: HKD=HK$, IDR=Rp, MYR=RM, USD=US$, BRL=R$, MXN=MXN$ and so on | K12: PASS | L12: MEDIUM | M12: KIMA | N12: 46272 | O12: Window OS | P12: Chromium | S12: Run
A13: TC_005 | B13: Wallet Chart | C13: The chart only names countries the account holds a wallet for | D13: Positive | E13: User is on the Wallet page | F13: -Given I log into the UMPay application with valid email credentials using "<row>" of "<excelSheetName>" of "<excelFileName>" -When I open the Wallet page -Then every country in the chart should be one the account holds a wallet for | G13: Valid UMPay user | H13: Every country in the assets chart should be one the account holds a wallet for | I13: User is on the Wallet page | J13: The chart named Indonesia, Vietnam, Philippines, Malaysia and Bangladesh, all of them wallets the account holds | K13: PASS | L13: MEDIUM | M13: KIMA | N13: 46272 | O13: Window OS | P13: Chromium | S13: Run
A14: TC_006 | B14: Wallet Detail | C14: A wallet opens its own page | D14: Positive | E14: User is on the Wallet page | F14: -Given I log into the UMPay application with valid email credentials using "<row>" of "<excelSheetName>" of "<excelFileName>" -When I open the Wallet page -And I open the wallet named in "<row>" of "<excelSheetName>" of "<excelFileName>" -Then that wallet's own page should open -And the wallet should state its total, what is available and what is locked | G14: Wallet: HKD | H14: Opening a wallet should go to that wallet's own page, stating its total, available and locked balances | I14: User is on the wallet's own page | J14: The HKD wallet opened at /v2/wallet/detail/record?currencyCode=HKD, stating all three balances | K14: PASS | L14: HIGH | M14: KIMA | N14: 46272 | O14: Window OS | P14: Chromium | S14: Run
A15: TC_007 | B15: Wallet Detail | C15: A wallet's total is what is available plus what is locked | D15: Positive | E15: User is on a wallet's own page | F15: -Given I log into the UMPay application with valid email credentials using "<row>" of "<excelSheetName>" of "<excelFileName>" -When I open the Wallet page -And I open the wallet named in "<row>" of "<excelSheetName>" of "<excelFileName>" -Then the wallet's total should be what is available plus what is locked | G15: Wallet: HKD | H15: The total balance should equal the available balance plus the amount locked | I15: User is on the wallet's own page | J15: 8369.51 available plus 5544.32 locked came to the stated total of 13913.83 | K15: PASS | L15: HIGH | M15: KIMA | N15: 46272 | O15: Window OS | P15: Chromium | S15: Run
A16: TC_008 | B16: Wallet Detail | C16: A wallet keeps what has moved and what is held in two tabs | D16: Positive | E16: User is on a wallet's own page | F16: -Given I log into the UMPay application with valid email credentials using "<row>" of "<excelSheetName>" of "<excelFileName>" -When I open the Wallet page -And I open the wallet named in "<row>" of "<excelSheetName>" of "<excelFileName>" -Then the wallet should offer the tabs "Record, Locked" | G16: Wallet: HKD | H16: The wallet should offer a Record tab and a Locked tab | I16: User is on the wallet's own page | J16: The wallet offered both the Record and Locked tabs | K16: PASS | L16: MEDIUM | M16: KIMA | N16: 46272 | O16: Window OS | P16: Chromium | S16: Run
A17: TC_009 | B17: Wallet Detail | C17: The Record tab lists what has moved in that wallet | D17: Positive | E17: User is on a wallet's own page | F17: -Given I log into the UMPay application with valid email credentials using "<row>" of "<excelSheetName>" of "<excelFileName>" -When I open the Wallet page -And I open the wallet named in "<row>" of "<excelSheetName>" of "<excelFileName>" -And I move to the wallet's "Record" tab -Then every movement should name what it was, when it happened and how much | G17: Wallet: HKD | H17: Every movement should name what it was, when it happened and how much | I17: User is on the wallet's own page | J17: The Record tab listed 20 movements, the newest being Convert 2026-09-07 15:44:33 HK$-1 | K17: PASS | L17: HIGH | M17: KIMA | N17: 46272 | O17: Window OS | P17: Chromium | S17: Run
A18: TC_010 | B18: Wallet Detail | C18: The Locked tab lists what is being held against that wallet | D18: Positive | E18: User is on a wallet's own page | F18: -Given I log into the UMPay application with valid email credentials using "<row>" of "<excelSheetName>" of "<excelFileName>" -When I open the Wallet page -And I open the wallet named in "<row>" of "<excelSheetName>" of "<excelFileName>" -And I move to the wallet's "Locked" tab -Then every movement should name what it was, when it happened and how much | G18: Wallet: HKD | H18: Every held amount should name what it was, when it happened and how much | I18: User is on the wallet's own page | J18: The Locked tab listed 20 held amounts, the newest being Withdraw 2026-09-07 12:28:22 HK$-107 | K18: PASS | L18: MEDIUM | M18: KIMA | N18: 46272 | O18: Window OS | P18: Chromium | S18: Run
A19: TC_011 | B19: Wallet Detail | C19: A wallet's own page offers to make it the main wallet | D19: Positive | E19: User is on a wallet's own page | F19: -Given I log into the UMPay application with valid email credentials using "<row>" of "<excelSheetName>" of "<excelFileName>" -When I open the Wallet page -And I open the wallet named in "<row>" of "<excelSheetName>" of "<excelFileName>" -Then the wallet should offer to become the main wallet | G19: Wallet: HKD | H19: The wallet should offer a Set as main button | I19: User is on the wallet's own page | J19: The wallet offered to become the main wallet | K19: PASS | L19: MEDIUM | M19: KIMA | N19: 46272 | O19: Window OS | P19: Chromium | S19: Run
A20: TC_012 | B20: Wallet Detail | C20: Going back from a wallet returns to the list | D20: Positive | E20: User is on a wallet's own page | F20: -Given I log into the UMPay application with valid email credentials using "<row>" of "<excelSheetName>" of "<excelFileName>" -When I open the Wallet page -And I open the wallet named in "<row>" of "<excelSheetName>" of "<excelFileName>" -Then that wallet's own page should open -When I go back to the wallets -Then the wallets should be listed again | G20: Wallet: HKD | H20: Going back should return to the list of wallets | I20: User is on the Wallet page | J20: Going back returned to the wallet list, all 10 still listed | K20: PASS | L20: MEDIUM | M20: KIMA | N20: 46272 | O20: Window OS | P20: Chromium | S20: Run
A21: TC_013 | B21: Wallet Main | C21: The main wallet can be moved to another wallet and put back | D21: Positive | E21: User is on the Wallet page | F21: -Given I log into the UMPay application with valid email credentials using "<row>" of "<excelSheetName>" of "<excelFileName>" -When I open the Wallet page -And I make the wallet named in "<row>" of "<excelSheetName>" of "<excelFileName>" the main one -Then that wallet should become the main one -When I put the main wallet back -Then the wallet that was main should be main again | G21: Move the main wallet to IDR | H21: The chosen wallet should become the main one, and setting the first one back should restore it | I21: The main wallet is as it was found | J21: The main wallet moved from HKD to IDR and was put back to HKD, with nothing asked first | K21: PASS | L21: HIGH | M21: KIMA | N21: 46272 | O21: Window OS | P21: Chromium | S21: Run

Sheet Payment
A1: Project Name | B1: UMPay
A2: Module/Feature Name | B2: Payment | P2: HIGH | Q2: MEDIUM | R2: LOW
A3: Reference Document | N3: PASS | O3: =COUNTIF(K:K,"PASS") | P3: =COUNTIFS(K:K,"PASS",L:L,"HIGH") | Q3: =COUNTIFS(K:K,"PASS",L:L,"MEDIUM") | R3: =COUNTIFS(K:K,"PASS",L:L,"LOW")
A4: Created By | B4: KIMA | N4: FAIL | O4: =COUNTIF(K:K,"FAIL") | P4: =COUNTIFS(K:K,"FAIL",L:L,"HIGH") | Q4: =COUNTIFS(K:K,"FAIL",L:L,"MEDIUM") | R4: =COUNTIFS(K:K,"FAIL",L:L,"LOW")
A5: Date of Creation | B5: 46272 | N5: PENDING | O5: =COUNTIF(K:K,"PENDING") | P5: =COUNTIFS(K:K,"PENDING",L:L,"HIGH") | Q5: =COUNTIFS(K:K,"PENDING",L:L,"MEDIUM") | R5: =COUNTIFS(K:K,"PENDING",L:L,"LOW")
A6: Date of Review | B6: 46272
A8: TEST CASE ID | B8: TEST SCENARIO | C8: TEST CASE | D8: TEST CATEGORY | E8: PRE-CONDITION | F8: TEST STEPS | G8: TEST DATA | H8: EXPECTED RESULTS | I8: POST CONDITION | J8: ACTUAL RESULT | K8: STATUS | L8: PRIORITY | M8: TESTER | N8: TEST DATE | O8: DEVICE | P8: BROWSER | Q8: ISSUE LINK | R8: COMMENT | S8: Run
A9: TC_001 | B9: Payment | C9: The profile drawer opens the account's payment accounts | D9: Positive | E9: User is signed in | F9: -Given I log into the UMPay application with valid email credentials using "<row>" of "<excelSheetName>" of "<excelFileName>" -When I open the Payment page -Then the page should list the payment accounts the account can be paid out to | G9: Valid UMPay user | H9: The payment page should open from the profile drawer, listing the accounts the user can be paid out to | I9: User is on the Payment page | J9: The drawer opened /settings-payment, listing 6 providers: AFIRME, Bangkok Bank Plc., DANA, HSBC, FPS, USDT-TRC 20 | K9: PASS | L9: HIGH | M9: KIMA | N9: 46272 | O9: Window OS | P9: Chromium | S9: Run
A10: TC_002 | B10: Payment List | C10: Every saved account names its provider and what identifies it | D10: Positive | E10: User is on the Payment page | F10: -Given I log into the UMPay application with valid email credentials using "<row>" of "<excelSheetName>" of "<excelFileName>" -When I open the Payment page -Then every saved account should name its provider and what identifies it | G10: Valid UMPay user | H10: Every saved account should name its provider and carry the details that identify it, with none of them blank | I10: User is on the Payment page | J10: Every saved account named its provider and carried its details, none of them blank | K10: PASS | L10: HIGH | M10: KIMA | N10: 46272 | O10: Window OS | P10: Chromium | S10: Run
A11: TC_003 | B11: Payment List | C11: Every saved account offers to be changed and removed | D11: Positive | E11: User is on the Payment page | F11: -Given I log into the UMPay application with valid email credentials using "<row>" of "<excelSheetName>" of "<excelFileName>" -When I open the Payment page -Then every saved account should offer to be changed and removed | G11: Valid UMPay user | H11: Each saved account should offer a way to change it and a way to remove it | I11: User is on the Payment page | J11: 12 payment accounts across 6 providers, each offering to be changed and removed | K11: PASS | L11: HIGH | M11: KIMA | N11: 46272 | O11: Window OS | P11: Chromium | S11: Run
A12: TC_004 | B12: Payment List | C12: A saved account can be opened to be changed | D12: Positive | E12: User is on the Payment page | F12: -Given I log into the UMPay application with valid email credentials using "<row>" of "<excelSheetName>" of "<excelFileName>" -When I open the Payment page -And I open the first saved account to change it -Then somewhere to change it should open | G12: Valid UMPay user | H12: Choosing to change a saved account should open somewhere it can be changed | I12: User is on the edit form | J12: Changing an account opened /settings-payment/create?mode=form&id=3024 | K12: PASS | L12: HIGH | M12: KIMA | N12: 46272 | O12: Window OS | P12: Chromium | S12: Run
A13: TC_005 | B13: Payment Add | C13: The page offers to add a payment account | D13: Positive | E13: User is on the Payment page | F13: -Given I log into the UMPay application with valid email credentials using "<row>" of "<excelSheetName>" of "<excelFileName>" -When I open the Payment page -And I start adding a payment account -Then the form for a new payment account should open | G13: Valid UMPay user | H13: Add Payment should open the form for a new payment account | I13: User is on the Add Payment form | J13: Add Payment opened /settings-payment/create | K13: PASS | L13: HIGH | M13: KIMA | N13: 46272 | O13: Window OS | P13: Chromium | S13: Run
A14: TC_006 | B14: Payment Add | C14: The form asks for a currency and offers every way of being paid | D14: Positive | E14: User is on the Add Payment form | F14: -Given I log into the UMPay application with valid email credentials using "<row>" of "<excelSheetName>" of "<excelFileName>" -When I open the Payment page -And I start adding a payment account -Then the form should ask for a currency and offer "E-Wallet, Bank, USDT" | G14: Valid UMPay user | H14: The form should state the currency and offer E-Wallet, Bank and USDT | I14: User is on the Add Payment form | J14: The form was set to Hong Kong and offered E-Wallet, Bank and USDT | K14: PASS | L14: HIGH | M14: KIMA | N14: 46272 | O14: Window OS | P14: Chromium | S14: Run
A15: TC_007 | B15: Payment Add | C15: Choosing to be paid by bank offers banks with their fees and how long they take | D15: Positive | E15: User is on the Add Payment form | F15: -Given I log into the UMPay application with valid email credentials using "<row>" of "<excelSheetName>" of "<excelFileName>" -When I open the Payment page -And I start adding a payment account -And I choose the way of being paid named in "<row>" of "<excelSheetName>" of "<excelFileName>" -Then the providers offered should each name how long they take and what they charge | G15: Way: Bank | H15: Every bank offered should name how long it takes and what it charges | I15: User is on the Add Payment form | J15: Offered 4 banks - Bank of China 6.20%, HSBC 6.00%, Hang Seng Bank 6.00%, Standard Chartered Bank 6.00% - each Duration:2mn | K15: PASS | L15: HIGH | M15: KIMA | N15: 46272 | O15: Window OS | P15: Chromium | S15: Run
A16: TC_008 | B16: Payment Add | C16: Choosing to be paid by e-wallet offers e-wallets with their fees and how long they take | D16: Positive | E16: User is on the Add Payment form | F16: -Given I log into the UMPay application with valid email credentials using "<row>" of "<excelSheetName>" of "<excelFileName>" -When I open the Payment page -And I start adding a payment account -And I choose the way of being paid named in "<row>" of "<excelSheetName>" of "<excelFileName>" -Then the providers offered should each name how long they take and what they charge | G16: Way: E-Wallet | H16: Every e-wallet offered should name how long it takes and what it charges | I16: User is on the Add Payment form | J16: Offered FPS, Duration:2mn, Fee Charge:7.00% | K16: PASS | L16: MEDIUM | M16: KIMA | N16: 46272 | O16: Window OS | P16: Chromium | S16: Run
A17: TC_009 | B17: Payment Add | C17: Choosing to be paid in USDT offers what it can be sent through | D17: Positive | E17: User is on the Add Payment form | F17: -Given I log into the UMPay application with valid email credentials using "<row>" of "<excelSheetName>" of "<excelFileName>" -When I open the Payment page -And I start adding a payment account -And I choose the way of being paid named in "<row>" of "<excelSheetName>" of "<excelFileName>" -Then the providers offered should each name how long they take and what they charge | G17: Way: USDT | H17: Every USDT network offered should name how long it takes and what it charges | I17: User is on the Add Payment form | J17: Offered USDT-TRC 20, Duration:1mn, Fee Charge:7.00% | K17: PASS | L17: MEDIUM | M17: KIMA | N17: 46272 | O17: Window OS | P17: Chromium | S17: Run
A18: TC_010 | B18: Payment Add | C18: The providers can be searched | D18: Positive | E18: A way of being paid has been chosen | F18: -Given I log into the UMPay application with valid email credentials using "<row>" of "<excelSheetName>" of "<excelFileName>" -When I open the Payment page -And I start adding a payment account -And I choose the way of being paid named in "<row>" of "<excelSheetName>" of "<excelFileName>" -Then the providers should be searchable | G18: Way: Bank | H18: The list of providers should offer a search | I18: User is on the Add Payment form | J18: The providers offered a search | K18: PASS | L18: MEDIUM | M18: KIMA | N18: 46272 | O18: Window OS | P18: Chromium | S18: Run
A19: TC_011 | B19: Payment Add | C19: Searching the providers leaves only what was searched for | D19: Positive | E19: A way of being paid has been chosen | F19: -Given I log into the UMPay application with valid email credentials using "<row>" of "<excelSheetName>" of "<excelFileName>" -When I open the Payment page -And I start adding a payment account -And I choose the way of being paid named in "<row>" of "<excelSheetName>" of "<excelFileName>" -And I search the providers for what is in "<row>" of "<excelSheetName>" of "<excelFileName>" -Then only the providers matching it should be left | G19: Search: Bank | H19: Only the providers whose name matches the search should be left | I19: User is on the Add Payment form | J19: Searching for Bank took 4 providers down to 3, all of them matching | K19: PASS | L19: HIGH | M19: KIMA | N19: 46272 | O19: Window OS | P19: Chromium | S19: Run
A20: TC_012 | B20: Payment Add | C20: Closing the providers leaves the form as it was | D20: Positive | E20: A way of being paid has been chosen | F20: -Given I log into the UMPay application with valid email credentials using "<row>" of "<excelSheetName>" of "<excelFileName>" -When I open the Payment page -And I start adding a payment account -And I choose the way of being paid named in "<row>" of "<excelSheetName>" of "<excelFileName>" -And I close what is being asked -Then the form should still be there | G20: Way: Bank | H20: Closing the list should leave the form with its currency and its ways of being paid | I20: User is on the Add Payment form | J20: The form was still there, offering E-Wallet, Bank and USDT | K20: PASS | L20: MEDIUM | M20: KIMA | N20: 46272 | O20: Window OS | P20: Chromium | S20: Run
... A25: TC_017 | B25: Payment | C25: Leaving a change form without saving leaves the account as it was | D25: Negative | E25: User is changing a saved payment account | F25: -Given I log into the UMPay application with valid email credentials using "<row>" of "<excelSheetName>" of "<excelFileName>" -When I open the Payment page -And I open the first saved account to change it -And I remember what the change form holds -And I empty the first detail the form insists on -And I go back to the payment accounts -And I open the first saved account to change it -Then the change form should hold what it held before | G25: Account Name: emptied, then abandoned | H25: Leaving the form without saving should change nothing, since a form that kept an emptied field on the way out would quietly break the withdraw and payout scenarios that pay into this account | I25: The account is unchanged | J25: The account held Account Name "test" and Account Number 5432552532. After emptying the Account Name, leaving the form and opening it again, it held exactly the same two values, so abandoning a change writes nothing back | K25: PASS | L25: HIGH | M25: KIMA | N25: 46273 | O25: Window OS | P25: Chromium | S25: Run

Sheet Template
A1: Project Name | B1: UMPay
A2: Module/Feature Name | B2: Template | P2: HIGH | Q2: MEDIUM | R2: LOW
A3: Reference Document | N3: PASS | O3: =COUNTIF(K:K,"PASS") | P3: =COUNTIFS(K:K,"PASS",L:L,"HIGH") | Q3: =COUNTIFS(K:K,"PASS",L:L,"MEDIUM") | R3: =COUNTIFS(K:K,"PASS",L:L,"LOW")
A4: Created By | B4: KIMA | N4: FAIL | O4: =COUNTIF(K:K,"FAIL") | P4: =COUNTIFS(K:K,"FAIL",L:L,"HIGH") | Q4: =COUNTIFS(K:K,"FAIL",L:L,"MEDIUM") | R4: =COUNTIFS(K:K,"FAIL",L:L,"LOW")
A5: Date of Creation | B5: 46273 | N5: PENDING | O5: =COUNTIF(K:K,"PENDING") | P5: =COUNTIFS(K:K,"PENDING",L:L,"HIGH") | Q5: =COUNTIFS(K:K,"PENDING",L:L,"MEDIUM") | R5: =COUNTIFS(K:K,"PENDING",L:L,"LOW")
A6: Date of Review | B6: 46273
A8: TEST CASE ID | B8: TEST SCENARIO | C8: TEST CASE | D8: TEST CATEGORY | E8: PRE-CONDITION | F8: TEST STEPS | G8: TEST DATA | H8: EXPECTED RESULTS | I8: POST CONDITION | J8: ACTUAL RESULT | K8: STATUS | L8: PRIORITY | M8: TESTER | N8: TEST DATE | O8: DEVICE | P8: BROWSER | Q8: ISSUE LINK | R8: COMMENT | S8: Run
A9: TC_001 | B9: Template | C9: The profile drawer opens the account's saved templates | D9: Positive | E9: User is signed in | F9: -Given I log into the UMPay application with valid email credentials using "<row>" of "<excelSheetName>" of "<excelFileName>" -When I open the Template page -Then the page should list the templates the account has saved | G9: Valid UMPay user | H9: The Templates page should open from the profile drawer, listing the destinations the user has saved | I9: User is on the Template page | J9: The drawer opened /v2/template, listing 10 saved templates - Outside China 2, Within China 3, Test, Within China 2, Outside China, Within China and four more | K9: PASS | L9: HIGH | M9: KIMA | N9: 46273 | O9: Window OS | P9: Chromium | S9: Run
A10: TC_002 | B10: Template List | C10: Every saved template names itself and the account it pays | D10: Positive | E10: User is on the Template page | F10: -Given I log into the UMPay application with valid email credentials using "<row>" of "<excelSheetName>" of "<excelFileName>" -When I open the Template page -Then every saved template should carry a name and the account it pays | G10: Valid UMPay user | H10: Every saved template should carry the name it was given and the account it pays, with neither of them blank | I10: User is on the Template page | J10: All 10 named themselves and what they pay, none blank. The first: "Outside China 2" paying **********000004 | K10: PASS | L10: HIGH | M10: KIMA | N10: 46273 | O10: Window OS | P10: Chromium | S10: Run
A11: TC_003 | B11: Template List | C11: Every saved template shows the way of sending it was saved for | D11: Positive | E11: User is on the Template page | F11: -Given I log into the UMPay application with valid email credentials using "<row>" of "<excelSheetName>" of "<excelFileName>" -When I open the Template page -Then every saved template should show the way of sending it was saved for | G11: Valid UMPay user | H11: Every saved template should show the way of sending money it was saved for | I11: User is on the Template page | J11: All 10 carried the picture of the way they were saved for - global-transfer, domestic-transfer, a school logo and the wallet initial | K11: PASS | L11: MEDIUM | M11: KIMA | N11: 46273 | O11: Window OS | P11: Chromium | S11: Run
A12: TC_004 | B12: Template List | C12: Every saved template offers to be changed and removed | D12: Positive | E12: User is on the Template page | F12: -Given I log into the UMPay application with valid email credentials using "<row>" of "<excelSheetName>" of "<excelFileName>" -When I open the Template page -Then every saved template should offer to be changed and removed | G12: Valid UMPay user | H12: Each saved template should offer a way to change it and a way to remove it | I12: User is on the Template page | J12: 10 saved templates, each offering both a pencil and a bin | K12: PASS | L12: HIGH | M12: KIMA | N12: 46273 | O12: Window OS | P12: Chromium | S12: Run
A13: TC_005 | B13: Template List | C13: A saved template can be opened to be changed | D13: Positive | E13: User is on the Template page | F13: -Given I log into the UMPay application with valid email credentials using "<row>" of "<excelSheetName>" of "<excelFileName>" -When I open the Template page -And I open the first saved template to change it -Then somewhere to change that template should open | G13: Valid UMPay user | H13: Choosing to change a saved template should open the form it was saved from, carrying that template | I13: User is on the form that changes the template | J13: The pencil opened /global-transfer/union-pay/receiver-info?update-template=&template-id=500, filled with that template and offering Update | K13: PASS | L13: HIGH | M13: KIMA | N13: 46273 | O13: Window OS | P13: Chromium | S13: Run
A14: TC_006 | B14: Template Add | C14: The page offers to add a template | D14: Positive | E14: User is on the Template page | F14: -Given I log into the UMPay application with valid email credentials using "<row>" of "<excelSheetName>" of "<excelFileName>" -When I open the Template page -And I start adding a template -Then the ways a template can be saved for should open | G14: Valid UMPay user | H14: Add Template should open the ways a template can be saved for | I14: User is on the Add Template options | J14: Add Template opened /v2/template/option | K14: PASS | L14: HIGH | M14: KIMA | N14: 46273 | O14: Window OS | P14: Chromium | S14: Run
A15: TC_007 | B15: Template Add | C15: Adding one offers every way a template can be saved for | D15: Positive | E15: User is on the Add Template options | F15: -Given I log into the UMPay application with valid email credentials using "<row>" of "<excelSheetName>" of "<excelFileName>" -When I open the Template page -And I start adding a template -Then the ways offered should be "UMPay to UMPay Wallet, UnionPay China, UnionPay Global, UMPay Transfer to School Fees, Transfer to Alipay, Transfer to Wechat" | G15: Valid UMPay user | H15: The page should offer UMPay to UMPay Wallet, UnionPay China, UnionPay Global, UMPay Transfer to School Fees, Transfer to Alipay and Transfer to Wechat | I15: User is on the Add Template options | J15: Offered all 6 - UMPay to UMPay Wallet, UnionPay China, UnionPay Global, UMPay Transfer to School Fees, Transfer to Alipay, Transfer to Wechat | K15: PASS | L15: HIGH | M15: KIMA | N15: 46273 | O15: Window OS | P15: Chromium | S15: Run
A16: TC_008 | B16: Template Add | C16: The ways that are closed say so | D16: Positive | E16: User is on the Add Template options | F16: -Given I log into the UMPay application with valid email credentials using "<row>" of "<excelSheetName>" of "<excelFileName>" -When I open the Template page -And I start adding a template -Then the ways "Transfer to Alipay, Transfer to Wechat" should be marked as under maintenance | G16: Valid UMPay user | H16: Transfer to Alipay and Transfer to Wechat should be marked as under maintenance | I16: User is on the Add Template options | J16: Transfer to Alipay and Transfer to Wechat were both marked Maintenance | K16: PASS | L16: MEDIUM | M16: KIMA | N16: 46273 | O16: Window OS | P16: Chromium | S16: Run
A17: TC_009 | B17: Template Add | C17: A template can be started for a UMPay wallet | D17: Positive | E17: User is on the Add Template options | F17: -Given I log into the UMPay application with valid email credentials using "<row>" of "<excelSheetName>" of "<excelFileName>" -When I open the Template page -And I start adding a template -And I choose the way named in "<row>" of "<excelSheetName>" of "<excelFileName>" -Then somewhere to save that template should open | G17: Route: UMPay to UMPay Wallet | H17: Choosing it should open somewhere to save the template, asking what to call it | I17: User is on the new template form | J17: Opened /v2/template/form, asking for a template name and a mobile, email or ID | K17: PASS | L17: HIGH | M17: KIMA | N17: 46273 | O17: Window OS | P17: Chromium | S17: Run
A18: TC_010 | B18: Template Add | C18: A template can be started for UnionPay China | D18: Positive | E18: User is on the Add Template options | F18: -Given I log into the UMPay application with valid email credentials using "<row>" of "<excelSheetName>" of "<excelFileName>" -When I open the Template page -And I start adding a template -And I choose the way named in "<row>" of "<excelSheetName>" of "<excelFileName>" -Then somewhere to save that template should open | G18: Route: UnionPay China | H18: Choosing it should open somewhere to save the template, asking what to call it | I18: User is on the new template form | J18: Opened /domestic-transfer/union-pay/receiver-info?create-template=, asking for a template name | K18: PASS | L18: HIGH | M18: KIMA | N18: 46273 | O18: Window OS | P18: Chromium | S18: Run
A19: TC_011 | B19: Template Add | C19: A template can be started for UnionPay Global | D19: Positive | E19: User is on the Add Template options | F19: -Given I log into the UMPay application with valid email credentials using "<row>" of "<excelSheetName>" of "<excelFileName>" -When I open the Template page -And I start adding a template -And I choose the way named in "<row>" of "<excelSheetName>" of "<excelFileName>" -Then somewhere to save that template should open | G19: Route: UnionPay Global | H19: Choosing it should open somewhere to save the template, asking what to call it | I19: User is on the new template form | J19: Opened /global-transfer/union-pay/receiver-info?create-template=, asking for a template name | K19: PASS | L19: HIGH | M19: KIMA | N19: 46273 | O19: Window OS | P19: Chromium | S19: Run
A20: TC_012 | B20: Template Add | C20: A template can be started for school fees | D20: Positive | E20: User is on the Add Template options | F20: -Given I log into the UMPay application with valid email credentials using "<row>" of "<excelSheetName>" of "<excelFileName>" -When I open the Template page -And I start adding a template -And I choose the way named in "<row>" of "<excelSheetName>" of "<excelFileName>" -Then somewhere to save that template should open | G20: Route: UMPay Transfer to School Fees | H20: Choosing it should open somewhere to save the template, asking what to call it | I20: User is on the new template form | J20: Opened /school-fee, asking for a template name | K20: PASS | L20: MEDIUM | M20: KIMA | N20: 46273 | O20: Window OS | P20: Chromium | S20: Run
... A22: TC_014 | B22: Template Add | C22: Going back from the ways returns to the saved templates | D22: Positive | E22: User is on the Add Template options | F22: -Given I log into the UMPay application with valid email credentials using "<row>" of "<excelSheetName>" of "<excelFileName>" -When I open the Template page -And I start adding a template -Then the ways a template can be saved for should open -When I go back to the saved templates -Then the saved templates should be listed again | G22: Valid UMPay user | H22: Going back should return to the list of saved templates, with all of them still there | I22: User is on the Template page | J22: Going back returned to the saved templates, all 10 still listed | K22: PASS | L22: MEDIUM | M22: KIMA | N22: 46273 | O22: Window OS | P22: Chromium | S22: Run

Sheet Transfer_Fee_Setting
A1: Project Name | B1: UMPay
A2: Module/Feature Name | B2: Transfer Fee Setting | P2: HIGH | Q2: MEDIUM | R2: LOW
A3: Reference Document | N3: PASS | O3: =COUNTIF(K:K,"PASS") | P3: =COUNTIFS(K:K,"PASS",L:L,"HIGH") | Q3: =COUNTIFS(K:K,"PASS",L:L,"MEDIUM") | R3: =COUNTIFS(K:K,"PASS",L:L,"LOW")
A4: Created By | B4: KIMA | N4: FAIL | O4: =COUNTIF(K:K,"FAIL") | P4: =COUNTIFS(K:K,"FAIL",L:L,"HIGH") | Q4: =COUNTIFS(K:K,"FAIL",L:L,"MEDIUM") | R4: =COUNTIFS(K:K,"FAIL",L:L,"LOW")
A5: Date of Creation | B5: 46273 | N5: PENDING | O5: =COUNTIF(K:K,"PENDING") | P5: =COUNTIFS(K:K,"PENDING",L:L,"HIGH") | Q5: =COUNTIFS(K:K,"PENDING",L:L,"MEDIUM") | R5: =COUNTIFS(K:K,"PENDING",L:L,"LOW")
A6: Date of Review | B6: 46273
A8: TEST CASE ID | B8: TEST SCENARIO | C8: TEST CASE | D8: TEST CATEGORY | E8: PRE-CONDITION | F8: TEST STEPS | G8: TEST DATA | H8: EXPECTED RESULTS | I8: POST CONDITION | J8: ACTUAL RESULT | K8: STATUS | L8: PRIORITY | M8: TESTER | N8: TEST DATE | O8: DEVICE | P8: BROWSER | Q8: ISSUE LINK | R8: COMMENT | S8: Run
A9: TC_001 | B9: Transfer Fee Setting | C9: The profile drawer opens the transfer fee setting | D9: Positive | E9: User is signed in | F9: -Given I log into the UMPay application with valid email credentials using "<row>" of "<excelSheetName>" of "<excelFileName>" -When I open the Transfer Fee Setting page -Then the transfer fee setting should be shown | G9: Valid UMPay user | H9: The Transfer Fee Setting page should open from the profile drawer, showing who pays the fee on this account transfers | I9: User is on the Transfer Fee Setting page | J9: The drawer opened /settings/transfer-fee, with the account on "Fee will be selected by User" (user) | K9: PASS | L9: HIGH | M9: KIMA | N9: 46273 | O9: Window OS | P9: Chromium | S9: Run
A10: TC_002 | B10: Transfer Fee Setting | C10: The page offers every way the fee can be settled | D10: Positive | E10: User is on the Transfer Fee Setting page | F10: -Given I log into the UMPay application with valid email credentials using "<row>" of "<excelSheetName>" of "<excelFileName>" -When I open the Transfer Fee Setting page -Then the ways of settling the fee should be "Fee will be selected by User, Fee will always be paid by other party, Fee will always be paid by me" | G10: Valid UMPay user | H10: The page should offer Fee will be selected by User, Fee will always be paid by other party and Fee will always be paid by me | I10: User is on the Transfer Fee Setting page | J10: Offered all 3 - Fee will be selected by User, Fee will always be paid by other party, Fee will always be paid by me | K10: PASS | L10: HIGH | M10: KIMA | N10: 46273 | O10: Window OS | P10: Chromium | S10: Run
A11: TC_003 | B11: Transfer Fee Setting | C11: Exactly one way is chosen, and the page says which | D11: Positive | E11: User is on the Transfer Fee Setting page | F11: -Given I log into the UMPay application with valid email credentials using "<row>" of "<excelSheetName>" of "<excelFileName>" -When I open the Transfer Fee Setting page -Then exactly one way of settling the fee should be chosen | G11: Valid UMPay user | H11: Exactly one of the three ways should be chosen, and the page should say which one | I11: User is on the Transfer Fee Setting page | J11: Exactly one was chosen: "Fee will be selected by User" (user) | K11: PASS | L11: HIGH | M11: KIMA | N11: 46273 | O11: Window OS | P11: Chromium | S11: Run
A12: TC_004 | B12: Transfer Fee Setting | C12: There is nothing to save until something is changed | D12: Negative | E12: User is on the Transfer Fee Setting page | F12: -Given I log into the UMPay application with valid email credentials using "<row>" of "<excelSheetName>" of "<excelFileName>" -When I open the Transfer Fee Setting page -Then the page should not offer to save anything | G12: Valid UMPay user | H12: Save should refuse to be pressed on a setting nobody has changed | I12: User is on the Transfer Fee Setting page | J12: Save refused to be pressed until a way had been changed | K12: PASS | L12: MEDIUM | M12: KIMA | N12: 46273 | O12: Window OS | P12: Chromium | S12: Run
A13: TC_005 | B13: Transfer Fee Setting | C13: Choosing another way offers to save it | D13: Positive | E13: User is on the Transfer Fee Setting page | F13: -Given I log into the UMPay application with valid email credentials using "<row>" of "<excelSheetName>" of "<excelFileName>" -When I open the Transfer Fee Setting page -And I choose the way of settling the fee named in "<row>" of "<excelSheetName>" of "<excelFileName>" -Then the page should offer to save it | G13: Way: Fee will always be paid by me | H13: Choosing a different way should bring Save alive so the change can be kept | I13: User is on the Transfer Fee Setting page | J13: Choosing "Fee will always be paid by me" brought Save alive | K13: PASS | L13: HIGH | M13: KIMA | N13: 46273 | O13: Window OS | P13: Chromium | S13: Run
A14: TC_006 | B14: Transfer Fee Setting | C14: Choosing a way leaves only that way chosen | D14: Positive | E14: User is on the Transfer Fee Setting page | F14: -Given I log into the UMPay application with valid email credentials using "<row>" of "<excelSheetName>" of "<excelFileName>" -When I open the Transfer Fee Setting page -And I choose the way of settling the fee named in "<row>" of "<excelSheetName>" of "<excelFileName>" -Then only that way should be chosen | G14: Way: Fee will always be paid by me | H14: Only the way just chosen should be chosen, since two of these would contradict the third | I14: User is on the Transfer Fee Setting page | J14: Only "Fee will always be paid by me" was left chosen, the other two cleared | K14: PASS | L14: HIGH | M14: KIMA | N14: 46273 | O14: Window OS | P14: Chromium | S14: Run
A15: TC_007 | B15: Transfer Fee Save | C15: The fee can be set to always be paid by me, and it stays | D15: Positive | E15: User is on the Transfer Fee Setting page | F15: -Given I log into the UMPay application with valid email credentials using "<row>" of "<excelSheetName>" of "<excelFileName>" -When I open the Transfer Fee Setting page -And I put the fee setting on the way named in "<row>" of "<excelSheetName>" of "<excelFileName>" -And I save the fee setting -Then the fee setting should still be that way when the page is opened again -When I put the fee setting back the way it was -Then the fee setting should be what it was before | G15: Way: Fee will always be paid by me | H15: The setting should save and still be that way when the page is opened again, and the account should then be put back the way it was found | I15: The account is back on the setting it started on | J15: DEFECT - Save does nothing. "Fee will always be paid by me" was chosen and Save pressed, but opening the page again showed "Fee will be selected by User". Pressing Save sends no request at all - checked by a real click, by a scripted click and by raising the form submit - and shows no message and raises no error | K15: FAIL | L15: HIGH | M15: KIMA | N15: 46273 | O15: Window OS | P15: Chromium | S15: Run
A16: TC_008 | B16: Transfer Fee Save | C16: The fee can be set to always be paid by the other party, and it stays | D16: Positive | E16: User is on the Transfer Fee Setting page | F16: -Given I log into the UMPay application with valid email credentials using "<row>" of "<excelSheetName>" of "<excelFileName>" -When I open the Transfer Fee Setting page -And I put the fee setting on the way named in "<row>" of "<excelSheetName>" of "<excelFileName>" -And I save the fee setting -Then the fee setting should still be that way when the page is opened again -When I put the fee setting back the way it was -Then the fee setting should be what it was before | G16: Way: Fee will always be paid by other party | H16: The setting should save and still be that way when the page is opened again, and the account should then be put back the way it was found | I16: The account is back on the setting it started on | J16: DEFECT - the same Save. "Fee will always be paid by other party" was chosen and saved, and opening the page again showed "Fee will be selected by User" | K16: FAIL | L16: HIGH | M16: KIMA | N16: 46273 | O16: Window OS | P16: Chromium | S16: Run
A17: TC_009 | B17: Transfer Fee Save | C17: The fee can be set to be chosen transfer by transfer, and it stays | D17: Positive | E17: User is on the Transfer Fee Setting page | F17: -Given I log into the UMPay application with valid email credentials using "<row>" of "<excelSheetName>" of "<excelFileName>" -When I open the Transfer Fee Setting page -And I put the fee setting on the way named in "<row>" of "<excelSheetName>" of "<excelFileName>" -And I save the fee setting -Then the fee setting should still be that way when the page is opened again -When I put the fee setting back the way it was -Then the fee setting should be what it was before | G17: Way: Fee will be selected by User | H17: The setting should be moved off this way and back to it, save, and still be that way when the page is opened again | I17: The account is back on the setting it started on | J17: DEFECT - blocked by the same Save. The setting was moved to "Fee will always be paid by other party" and saved; that save did not keep, so returning to "Fee will be selected by User" was no change at all and Save stayed dead | K17: FAIL | L17: HIGH | M17: KIMA | N17: 46273 | O17: Window OS | P17: Chromium | S17: Run
A18: TC_010 | B18: Transfer Fee Save | C18: Leaving without saving leaves the setting as it was | D18: Negative | E18: User is on the Transfer Fee Setting page | F18: -Given I log into the UMPay application with valid email credentials using "<row>" of "<excelSheetName>" of "<excelFileName>" -When I open the Transfer Fee Setting page -And I choose the way of settling the fee named in "<row>" of "<excelSheetName>" of "<excelFileName>" -And I leave the page without saving -Then the fee setting should be what it was before | G18: Way: Fee will always be paid by other party | H18: A way chosen but not saved should be forgotten when the page is left, leaving the account on the setting it was on | I18: The account is on the setting it started on | J18: Choosing "Fee will always be paid by other party" and leaving the page left the account on "Fee will be selected by User" | K18: PASS | L18: HIGH | M18: KIMA | N18: 46273 | O18: Window OS | P18: Chromium | S18: Run

Sheet Security
A1: Project Name | B1: UMPay
A2: Module/Feature Name | B2: Security | P2: HIGH | Q2: MEDIUM | R2: LOW
A3: Reference Document | N3: PASS | O3: =COUNTIF(K:K,"PASS") | P3: =COUNTIFS(K:K,"PASS",L:L,"HIGH") | Q3: =COUNTIFS(K:K,"PASS",L:L,"MEDIUM") | R3: =COUNTIFS(K:K,"PASS",L:L,"LOW")
A4: Created By | B4: KIMA | N4: FAIL | O4: =COUNTIF(K:K,"FAIL") | P4: =COUNTIFS(K:K,"FAIL",L:L,"HIGH") | Q4: =COUNTIFS(K:K,"FAIL",L:L,"MEDIUM") | R4: =COUNTIFS(K:K,"FAIL",L:L,"LOW")
A5: Date of Creation | B5: 46273 | N5: PENDING | O5: =COUNTIF(K:K,"PENDING") | P5: =COUNTIFS(K:K,"PENDING",L:L,"HIGH") | Q5: =COUNTIFS(K:K,"PENDING",L:L,"MEDIUM") | R5: =COUNTIFS(K:K,"PENDING",L:L,"LOW")
A6: Date of Review | B6: 46273
A8: TEST CASE ID | B8: TEST SCENARIO | C8: TEST CASE | D8: TEST CATEGORY | E8: PRE-CONDITION | F8: TEST STEPS | G8: TEST DATA | H8: EXPECTED RESULTS | I8: POST CONDITION | J8: ACTUAL RESULT | K8: STATUS | L8: PRIORITY | M8: TESTER | N8: TEST DATE | O8: DEVICE | P8: BROWSER | Q8: ISSUE LINK | R8: COMMENT | S8: Run
A9: TC_001 | B9: Security | C9: The profile drawer opens what guards the account | D9: Positive | E9: User is signed in | F9: -Given I log into the UMPay application with valid email credentials using "<row>" of "<excelSheetName>" of "<excelFileName>" -When I open the Security page -Then the page should list what guards the account | G9: Valid UMPay user | H9: The Security page should open from the profile drawer, listing what guards the account | I9: User is on the Security page | J9: The drawer opened /securities, listing Login Password, PIN Code and 2FA Authenticator | K9: PASS | L9: HIGH | M9: KIMA | N9: 46273 | O9: Window OS | P9: Chromium | S9: Run
A10: TC_002 | B10: Security | C10: The page offers everything the account is guarded by | D10: Positive | E10: User is on the Security page | F10: -Given I log into the UMPay application with valid email credentials using "<row>" of "<excelSheetName>" of "<excelFileName>" -When I open the Security page -Then what guards the account should be "Login Password, PIN Code, 2FA Authenticator" | G10: Valid UMPay user | H10: The page should offer Login Password, PIN Code and 2FA Authenticator | I10: User is on the Security page | J10: Offered all 3 - Login Password, PIN Code, 2FA Authenticator | K10: PASS | L10: HIGH | M10: KIMA | N10: 46273 | O10: Window OS | P10: Chromium | S10: Run
A11: TC_003 | B11: Security | C11: The page says whether the authenticator is connected | D11: Positive | E11: User is on the Security page | F11: -Given I log into the UMPay application with valid email credentials using "<row>" of "<excelSheetName>" of "<excelFileName>" -When I open the Security page -Then the authenticator should say whether it is connected | G11: Valid UMPay user | H11: The 2FA Authenticator row should say where it stands, so a second factor can be seen to be on or off | I11: User is on the Security page | J11: The 2FA Authenticator row said "Connected" | K11: PASS | L11: HIGH | M11: KIMA | N11: 46273 | O11: Window OS | P11: Chromium | S11: Run
A12: TC_004 | B12: Security Password | C12: Login Password opens the form that changes it | D12: Positive | E12: User is on the Security page | F12: -Given I log into the UMPay application with valid email credentials using "<row>" of "<excelSheetName>" of "<excelFileName>" -When I open the Security page -And I open "Login Password" from the security page -Then the form that changes the login password should open | G12: Valid UMPay user | H12: Login Password should open the change form, asking for the current password, a new one and a confirmation | I12: User is on the Change Password form | J12: Opened /securities/password, asking for current_password, new_password and confirm_password | K12: PASS | L12: HIGH | M12: KIMA | N12: 46273 | O12: Window OS | P12: Chromium | S12: Run
A13: TC_005 | B13: Security Password | C13: Everything the password form asks for is hidden as it is typed | D13: Positive | E13: User is on the Change Password form | F13: -Given I log into the UMPay application with valid email credentials using "<row>" of "<excelSheetName>" of "<excelFileName>" -When I open the Security page -And I open "Login Password" from the security page -Then everything it asks for should be hidden as it is typed | G13: Valid UMPay user | H13: Every box on the form should hide what is typed into it | I13: User is on the Change Password form | J13: All 3 boxes were password boxes, hiding what is typed into them | K13: PASS | L13: HIGH | M13: KIMA | N13: 46273 | O13: Window OS | P13: Chromium | S13: Run
A14: TC_006 | B14: Security Password | C14: A password change with nothing filled in is refused | D14: Negative | E14: User is on the Change Password form | F14: -Given I log into the UMPay application with valid email credentials using "<row>" of "<excelSheetName>" of "<excelFileName>" -When I open the Security page -And I open "Login Password" from the security page -And I fill the password form from "<row>" of "<excelSheetName>" of "<excelFileName>" -And I save the change -Then the change should be refused | G14: Current EMPTY, New EMPTY, Confirm EMPTY | H14: Saving an empty form should be refused and leave the password as it is | I14: The account still signs in with the password it had | J14: Saving an empty form was refused - the run stayed on the form and nothing was saved | K14: PASS | L14: HIGH | M14: KIMA | N14: 46273 | O14: Window OS | P14: Chromium | S14: Run
A15: TC_007 | B15: Security Password | C15: A password change with no new password is refused | D15: Negative | E15: User is on the Change Password form | F15: -Given I log into the UMPay application with valid email credentials using "<row>" of "<excelSheetName>" of "<excelFileName>" -When I open the Security page -And I open "Login Password" from the security page -And I fill the password form from "<row>" of "<excelSheetName>" of "<excelFileName>" -And I save the change -Then the change should be refused | G15: Current 12345678, New EMPTY, Confirm SomethingElse123 | H15: Saving with no new password should be refused and leave the password as it is | I15: The account still signs in with the password it had | J15: Saving with the current password filled and no new one was refused - the run stayed on the form and nothing was saved | K15: PASS | L15: HIGH | M15: KIMA | N15: 46273 | O15: Window OS | P15: Chromium | S15: Run
A16: TC_008 | B16: Security PIN | C16: PIN Code opens the form that changes it, and says what a PIN may be | D16: Positive | E16: User is on the Security page | F16: -Given I log into the UMPay application with valid email credentials using "<row>" of "<excelSheetName>" of "<excelFileName>" -When I open the Security page -And I open "PIN Code" from the security page -Then the form that changes the PIN should open, saying what a PIN may be | G16: Valid UMPay user | H16: PIN Code should open the change form, taking 4 digits a box and stating what a PIN may be | I16: User is on the Change PIN form | J16: Opened /securities/pin, taking 4 digits a box and saying "Enter 4-digit PIN, The PIN code can not be the all same numbers or using a sequential numbers" | K16: PASS | L16: HIGH | M16: KIMA | N16: 46273 | O16: Window OS | P16: Chromium | S16: Run
A17: TC_009 | B17: Security PIN | C17: A PIN change with nothing filled in is refused | D17: Negative | E17: User is on the Change PIN form | F17: -Given I log into the UMPay application with valid email credentials using "<row>" of "<excelSheetName>" of "<excelFileName>" -When I open the Security page -And I open "PIN Code" from the security page -And I fill the PIN form from "<row>" of "<excelSheetName>" of "<excelFileName>" -And I save the change -Then the change should be refused | G17: Current EMPTY, New EMPTY, Confirm EMPTY | H17: Saving an empty form should be refused and leave the PIN as it is | I17: The account still has the PIN it had | J17: Saving an empty form was refused - the run stayed on the form and nothing was saved | K17: PASS | L17: HIGH | M17: KIMA | N17: 46273 | O17: Window OS | P17: Chromium | S17: Run
A18: TC_010 | B18: Security PIN | C18: A PIN change whose confirmation does not match is refused | D18: Negative | E18: User is on the Change PIN form | F18: -Given I log into the UMPay application with valid email credentials using "<row>" of "<excelSheetName>" of "<excelFileName>" -When I open the Security page -And I open "PIN Code" from the security page -And I fill the PIN form from "<row>" of "<excelSheetName>" of "<excelFileName>" -And I save the change -Then the change should be refused | G18: Current 1111, New 1234, Confirm 4321 | H18: A new PIN mistyped in the confirm box should be refused and leave the PIN as it is | I18: The account still has the PIN it had | J18: New 1234 against a confirm of 4321 was refused - the run stayed on the form and the PIN was unchanged | K18: PASS | L18: HIGH | M18: KIMA | N18: 46273 | O18: Window OS | P18: Chromium | S18: Run
A19: TC_011 | B19: Security PIN | C19: A PIN made of one digit repeated is refused, as the page requires | D19: Negative | E19: User is on the Change PIN form | F19: -Given I log into the UMPay application with valid email credentials using "<row>" of "<excelSheetName>" of "<excelFileName>" -When I open the Security page -And I open "PIN Code" from the security page -And I fill the PIN form from "<row>" of "<excelSheetName>" of "<excelFileName>" -And I save the change -Then the PIN should be refused, as the page requires | G19: Current 1111, New 1111, Confirm 1111 - the PIN already set, so being accepted changes nothing | H19: The page states that a PIN may not be all the same numbers, so a repeated digit should be refused | I19: The account still has the PIN it had | J19: DEFECT - the PIN form took 1111, a PIN of one digit repeated, answered "Updated successfully" and left for the Wallets page, though the form itself says "The PIN code can not be the all same numbers or using a sequential numbers". The PIN submitted was the one the account already had, so nothing about this account changed | K19: FAIL | L19: HIGH | M19: KIMA | N19: 46273 | O19: Window OS | P19: Chromium | S19: Run
A20: TC_012 | B20: Security 2FA | C20: The authenticator says it is connected and offers to remove or reset it | D20: Positive | E20: User is on the Security page | F20: -Given I log into the UMPay application with valid email credentials using "<row>" of "<excelSheetName>" of "<excelFileName>" -When I open the Security page -And I open "2FA Authenticator" from the security page -Then the authenticator should be connected and offer to be removed or reset | G20: Valid UMPay user | H20: The authenticator page should say it is connected and offer both removing and resetting it | I20: User is on the 2FA Authenticator page | J20: Opened /securities/two-factor, saying Connected and offering both "Remove Google Authenticator" and "Reset 2FA Google Authenticator". Neither was pressed | K20: PASS | L20: HIGH | M20: KIMA | N20: 46273 | O20: Window OS | P20: Chromium | S20: Run
A21: TC_013 | B21: Security | C21: Going back from a change form returns to what guards the account | D21: Positive | E21: User is on the Change Password form | F21: -Given I log into the UMPay application with valid email credentials using "<row>" of "<excelSheetName>" of "<excelFileName>" -When I open the Security page -And I open "Login Password" from the security page -Then the form that changes the login password should open -When I go back to what guards the account -Then what guards the account should be listed again | G21: Valid UMPay user | H21: Going back should return to the security page with all three things still listed | I21: User is on the Security page | J21: Going back returned to /securities with all three still listed | K21: PASS | L21: MEDIUM | M21: KIMA | N21: 46273 | O21: Window OS | P21: Chromium | S21: Run

Sheet Languages
A1: Project Name | B1: UMPay
A2: Module/Feature Name | B2: Languages | P2: HIGH | Q2: MEDIUM | R2: LOW
A3: Reference Document | N3: PASS | O3: =COUNTIF(K:K,"PASS") | P3: =COUNTIFS(K:K,"PASS",L:L,"HIGH") | Q3: =COUNTIFS(K:K,"PASS",L:L,"MEDIUM") | R3: =COUNTIFS(K:K,"PASS",L:L,"LOW")
A4: Created By | B4: KIMA | N4: FAIL | O4: =COUNTIF(K:K,"FAIL") | P4: =COUNTIFS(K:K,"FAIL",L:L,"HIGH") | Q4: =COUNTIFS(K:K,"FAIL",L:L,"MEDIUM") | R4: =COUNTIFS(K:K,"FAIL",L:L,"LOW")
A5: Date of Creation | B5: 46273 | N5: PENDING | O5: =COUNTIF(K:K,"PENDING") | P5: =COUNTIFS(K:K,"PENDING",L:L,"HIGH") | Q5: =COUNTIFS(K:K,"PENDING",L:L,"MEDIUM") | R5: =COUNTIFS(K:K,"PENDING",L:L,"LOW")
A6: Date of Review | B6: 46273
A8: TEST CASE ID | B8: TEST SCENARIO | C8: TEST CASE | D8: TEST CATEGORY | E8: PRE-CONDITION | F8: TEST STEPS | G8: TEST DATA | H8: EXPECTED RESULTS | I8: POST CONDITION | J8: ACTUAL RESULT | K8: STATUS | L8: PRIORITY | M8: TESTER | N8: TEST DATE | O8: DEVICE | P8: BROWSER | Q8: ISSUE LINK | R8: COMMENT | S8: Run
A9: TC_001 | B9: Languages | C9: The profile drawer opens the languages | D9: Positive | E9: User is signed in | F9: -Given I log into the UMPay application with valid email credentials using "<row>" of "<excelSheetName>" of "<excelFileName>" -When I open the Languages page -Then the languages should be shown | G9: Valid UMPay user | H9: The Languages page should open from the profile drawer, offering the languages the account can be read in | I9: User is on the Languages page | J9: The drawer opened /v2/languages, offering en, zh-HK and th, with the account on English | K9: PASS | L9: HIGH | M9: KIMA | N9: 46273 | O9: Window OS | P9: Chromium | S9: Run
A10: TC_002 | B10: Languages | C10: The page offers every language the account can be read in | D10: Positive | E10: User is on the Languages page | F10: -Given I log into the UMPay application with valid email credentials using "<row>" of "<excelSheetName>" of "<excelFileName>" -When I open the Languages page -Then the languages offered should be "en, zh-HK, th" | G10: Valid UMPay user | H10: The page should offer English (en), Chinese (zh-HK) and Thai (th) | I10: User is on the Languages page | J10: Offered all 3 - English (en), 繁體中文 (zh-HK) and ไทย (th) | K10: PASS | L10: HIGH | M10: KIMA | N10: 46273 | O10: Window OS | P10: Chromium | S10: Run
A11: TC_003 | B11: Languages | C11: Every language is written in its own script | D11: Positive | E11: User is on the Languages page | F11: -Given I log into the UMPay application with valid email credentials using "<row>" of "<excelSheetName>" of "<excelFileName>" -When I open the Languages page -Then every language should be named in its own script | G11: Valid UMPay user | H11: Each language should name itself in its own script, so somebody who cannot read the current one can still find theirs | I11: User is on the Languages page | J11: Each named itself in its own script - English, 繁體中文, ไทย - so none of them needs English to be found | K11: PASS | L11: MEDIUM | M11: KIMA | N11: 46273 | O11: Window OS | P11: Chromium | S11: Run
A12: TC_004 | B12: Languages | C12: Exactly one language is chosen, and the page says which | D12: Positive | E12: User is on the Languages page | F12: -Given I log into the UMPay application with valid email credentials using "<row>" of "<excelSheetName>" of "<excelFileName>" -When I open the Languages page -Then exactly one language should be chosen | G12: Valid UMPay user | H12: Exactly one of the three should be chosen, and the page should say which | I12: User is on the Languages page | J12: Exactly one was chosen: English (en) | K12: PASS | L12: HIGH | M12: KIMA | N12: 46273 | O12: Window OS | P12: Chromium | S12: Run
A13: TC_005 | B13: Languages | C13: The language is chosen without anything to save | D13: Positive | E13: User is on the Languages page | F13: -Given I log into the UMPay application with valid email credentials using "<row>" of "<excelSheetName>" of "<excelFileName>" -When I open the Languages page -Then the page should offer nothing to save | G13: Valid UMPay user | H13: The page should offer nothing to save - choosing a language should be the whole of it | I13: User is on the Languages page | J13: The page offered nothing to save - choosing a language is the whole of it | K13: PASS | L13: MEDIUM | M13: KIMA | N13: 46273 | O13: Window OS | P13: Chromium | S13: Run
A14: TC_006 | B14: Languages Switch | C14: The application can be read in Chinese | D14: Positive | E14: User is on the Languages page | F14: -Given I log into the UMPay application with valid email credentials using "<row>" of "<excelSheetName>" of "<excelFileName>" -When I open the Languages page -And I put the language on the one named in "<row>" of "<excelSheetName>" of "<excelFileName>" -Then the interface should come back in that language -When I put the language back the way it was -Then the interface should be back in the language it was in | G14: Language: zh-HK | H14: Choosing Chinese should bring the interface back in Chinese, and the account should then be put back on the language it was found on | I14: The account is back in the language it started in | J14: Choosing zh-HK brought the interface back in Chinese - the tab read "UMPay | 語言" where in English it read "UMPay | Languages" - and the account was put back on en | K14: PASS | L14: HIGH | M14: KIMA | N14: 46273 | O14: Window OS | P14: Chromium | S14: Run
A15: TC_007 | B15: Languages Switch | C15: The application can be read in Thai | D15: Positive | E15: User is on the Languages page | F15: -Given I log into the UMPay application with valid email credentials using "<row>" of "<excelSheetName>" of "<excelFileName>" -When I open the Languages page -And I put the language on the one named in "<row>" of "<excelSheetName>" of "<excelFileName>" -Then the interface should come back in that language -When I put the language back the way it was -Then the interface should be back in the language it was in | G15: Language: th | H15: Choosing Thai should bring the interface back in Thai, and the account should then be put back on the language it was found on | I15: The account is back in the language it started in | J15: Choosing th brought the interface back in Thai, the tab reading in Thai script where in English it read "UMPay | Languages", and the account was put back on en | K15: PASS | L15: HIGH | M15: KIMA | N15: 46273 | O15: Window OS | P15: Chromium | S15: Run
A16: TC_008 | B16: Languages Switch | C16: Choosing a language leaves only that language chosen | D16: Positive | E16: User is on the Languages page | F16: -Given I log into the UMPay application with valid email credentials using "<row>" of "<excelSheetName>" of "<excelFileName>" -When I open the Languages page -And I put the language on the one named in "<row>" of "<excelSheetName>" of "<excelFileName>" -Then only that language should be chosen -When I put the language back the way it was -Then the interface should be back in the language it was in | G16: Language: zh-HK | H16: Only the language just chosen should be chosen, since the application could not act on two | I16: The account is back in the language it started in | J16: Choosing zh-HK left only zh-HK chosen, and the account was put back on en | K16: PASS | L16: HIGH | M16: KIMA | N16: 46273 | O16: Window OS | P16: Chromium | S16: Run
A17: TC_009 | B17: Languages Switch | C17: A chosen language is still chosen when the page is opened again | D17: Positive | E17: User is on the Languages page | F17: -Given I log into the UMPay application with valid email credentials using "<row>" of "<excelSheetName>" of "<excelFileName>" -When I open the Languages page -And I put the language on the one named in "<row>" of "<excelSheetName>" of "<excelFileName>" -Then it should still be chosen when the page is opened again -When I put the language back the way it was -Then the interface should be back in the language it was in | G17: Language: zh-HK | H17: The chosen language should still be chosen when the page is opened again | I17: The account is back in the language it started in | J17: zh-HK was still chosen when the page was opened again, and the account was put back on en | K17: PASS | L17: HIGH | M17: KIMA | N17: 46273 | O17: Window OS | P17: Chromium | S17: Run
A18: TC_010 | B18: Languages Switch | C18: The language follows the account onto another page | D18: Positive | E18: User is on the Languages page | F18: -Given I log into the UMPay application with valid email credentials using "<row>" of "<excelSheetName>" of "<excelFileName>" -When I open the Languages page -And I put the language on the one named in "<row>" of "<excelSheetName>" of "<excelFileName>" -And I go to the home page -Then the interface should still be in that language -When I put the language back the way it was -Then the interface should be back in the language it was in | G18: Language: zh-HK | H18: The interface should still be in the chosen language on the home page, since the language belongs to the account rather than to the page it was chosen on | I18: The account is back in the language it started in | J18: On the home page the tab read "UMPay | 主頁" in zh-HK, so the language belongs to the account rather than to the page it was chosen on, and the account was put back on en | K18: PASS | L18: MEDIUM | M18: KIMA | N18: 46273 | O18: Window OS | P18: Chromium | S18: Run

Sheet Settings
A1: Project Name | B1: UMPay
A2: Module/Feature Name | B2: Settings | P2: HIGH | Q2: MEDIUM | R2: LOW
A3: Reference Document | N3: PASS | O3: =COUNTIF(K:K,"PASS") | P3: =COUNTIFS(K:K,"PASS",L:L,"HIGH") | Q3: =COUNTIFS(K:K,"PASS",L:L,"MEDIUM") | R3: =COUNTIFS(K:K,"PASS",L:L,"LOW")
A4: Created By | B4: KIMA | N4: FAIL | O4: =COUNTIF(K:K,"FAIL") | P4: =COUNTIFS(K:K,"FAIL",L:L,"HIGH") | Q4: =COUNTIFS(K:K,"FAIL",L:L,"MEDIUM") | R4: =COUNTIFS(K:K,"FAIL",L:L,"LOW")
A5: Date of Creation | B5: 46273 | N5: PENDING | O5: =COUNTIF(K:K,"PENDING") | P5: =COUNTIFS(K:K,"PENDING",L:L,"HIGH") | Q5: =COUNTIFS(K:K,"PENDING",L:L,"MEDIUM") | R5: =COUNTIFS(K:K,"PENDING",L:L,"LOW")
A6: Date of Review | B6: 46273
A8: TEST CASE ID | B8: TEST SCENARIO | C8: TEST CASE | D8: TEST CATEGORY | E8: PRE-CONDITION | F8: TEST STEPS | G8: TEST DATA | H8: EXPECTED RESULTS | I8: POST CONDITION | J8: ACTUAL RESULT | K8: STATUS | L8: PRIORITY | M8: TESTER | N8: TEST DATE | O8: DEVICE | P8: BROWSER | Q8: ISSUE LINK | R8: COMMENT | S8: Run
A9: TC_001 | B9: Settings | C9: The profile drawer opens the settings | D9: Positive | E9: User is signed in | F9: -Given I log into the UMPay application with valid email credentials using "<row>" of "<excelSheetName>" of "<excelFileName>" -When I open the Settings page -Then the settings should be shown | G9: Valid UMPay user | H9: The Settings page should open from the profile drawer, listing what can be set | I9: User is on the Settings page | J9: The drawer opened /settings, offering Auto Logout, About UMPay, Email and Phone Number | K9: PASS | L9: HIGH | M9: KIMA | N9: 46273 | O9: Window OS | P9: Chromium | S9: Run
A10: TC_002 | B10: Settings | C10: The page offers everything that can be set | D10: Positive | E10: User is on the Settings page | F10: -Given I log into the UMPay application with valid email credentials using "<row>" of "<excelSheetName>" of "<excelFileName>" -When I open the Settings page -Then the settings offered should be "Auto Logout, About UMPay, Email, Phone Number" | G10: Valid UMPay user | H10: The page should offer Auto Logout, About UMPay, Email and Phone Number | I10: User is on the Settings page | J10: Offered all 4 - Auto Logout, About UMPay, Email, Phone Number | K10: PASS | L10: HIGH | M10: KIMA | N10: 46273 | O10: Window OS | P10: Chromium | S10: Run
A11: TC_003 | B11: Settings Auto Logout | C11: Auto Logout says how long the account may sit idle | D11: Positive | E11: User is on the Settings page | F11: -Given I log into the UMPay application with valid email credentials using "<row>" of "<excelSheetName>" of "<excelFileName>" -When I open the Settings page -And I open "Auto Logout" from the settings -Then the auto logout should say how long the account may sit idle | G11: Valid UMPay user | H11: Auto Logout should open, saying after how many minutes of sitting still it acts, and offering both Save and Reset | I11: User is on the Auto Logout page | J11: Opened /settings/logout: the auto logout is off, set to 31 minutes of sitting still, and offers both Save and Reset | K11: PASS | L11: HIGH | M11: KIMA | N11: 46273 | O11: Window OS | P11: Chromium | S11: Run
A12: TC_004 | B12: Settings Auto Logout | C12: Auto Logout offers to leave an order in flight alone | D12: Positive | E12: User is on the Auto Logout page | F12: -Given I log into the UMPay application with valid email credentials using "<row>" of "<excelSheetName>" of "<excelFileName>" -When I open the Settings page -And I open "Auto Logout" from the settings -Then it should offer to leave an order in flight alone | G12: Valid UMPay user | H12: The page should offer to leave an order in flight alone, so nobody is thrown out halfway through paying | I12: User is on the Auto Logout page | J12: The page offers "Do not log me out if I have an active order", which is currently on | K12: PASS | L12: MEDIUM | M12: KIMA | N12: 46273 | O12: Window OS | P12: Chromium | S12: Run
A13: TC_005 | B13: Settings Auto Logout | C13: The minutes can be put up and down | D13: Positive | E13: User is on the Auto Logout page | F13: -Given I log into the UMPay application with valid email credentials using "<row>" of "<excelSheetName>" of "<excelFileName>" -When I open the Settings page -And I open "Auto Logout" from the settings -And I put the minutes up -Then the minutes should have gone up -When I put the minutes down -Then the minutes should be back where they started | G13: Valid UMPay user | H13: Pressing + should put the minutes up and pressing - should bring them back to where they started | I13: The minutes are back where they started, and nothing is saved | J13: One press of + took the minutes from 31 to 33 - the stepper moves in twos - and one press of - brought them back to 31 | K13: PASS | L13: HIGH | M13: KIMA | N13: 46273 | O13: Window OS | P13: Chromium | S13: Run
A14: TC_006 | B14: Settings Auto Logout | C14: Leaving the auto logout without saving leaves it as it was | D14: Negative | E14: The minutes have been changed and not saved | F14: -Given I log into the UMPay application with valid email credentials using "<row>" of "<excelSheetName>" of "<excelFileName>" -When I open the Settings page -And I open "Auto Logout" from the settings -And I put the minutes up -And I leave the auto logout without saving -Then the auto logout should be as it was | G14: Valid UMPay user | H14: Leaving the page without saving should leave the auto logout on the minutes the account was already on | I14: The account keeps the auto logout it had | J14: The minutes were put up and the page left without saving; opened again it read 31 minutes, still off, exactly as it was found | K14: PASS | L14: HIGH | M14: KIMA | N14: 46273 | O14: Window OS | P14: Chromium | S14: Run
A15: TC_007 | B15: Settings About | C15: About UMPay carries the terms and where UMPay can be followed | D15: Positive | E15: User is on the Settings page | F15: -Given I log into the UMPay application with valid email credentials using "<row>" of "<excelSheetName>" of "<excelFileName>" -When I open the Settings page -And I open "About UMPay" from the settings -Then it should offer "Terms and Conditions, Facebook, Instagram, X, Youtube" | G15: Valid UMPay user | H15: About UMPay should carry the Terms and Conditions and the places UMPay can be followed - Facebook, Instagram, X and Youtube | I15: User is on the About UMPay page | J15: Opened /settings/about carrying the Terms and Conditions and all four places - Facebook, Instagram, X and Youtube | K15: PASS | L15: MEDIUM | M15: KIMA | N15: 46273 | O15: Window OS | P15: Chromium | S15: Run
